Workbook

Sheet Team Directory
A1: WITYLOGIX — STARTUP ENGINEERING TEAM
A2: 9-person team organized into 5 squads — working in parallel across 6 phases
A4: ID | B4: Name | C4: Role | D4: Squad | E4: Focus Areas | F4: Parallel Tracks | G4: Models | H4: Pages | I4: Services | J4: Infra | K4: Roadmap | L4: Total Items
A5: AR | B5: Arjun Rajput | C5: CTO / Tech Lead | D5: Architecture | E5: System design, API architecture, DB schema, auth, infra decisions | F5: Auth system, RBAC, schema design, code reviews | G5: =COUNTIF('Data Models Gap'!I:I,"*AR*") -> 6 | H5: =COUNTIF('Feature Gap - Pages'!H:H,"*AR*") -> 1 | I5: =COUNTIF('Service & API Gap'!H:H,"*AR*") -> 6 | J5: =COUNTIF('Infrastructure Gap'!H:H,"*AR*") -> 2 | K5: =COUNTIF('Priority Roadmap'!I:I,"*AR*") -> 3 | L5: =SUM(G5:K5) -> 18
A6: PK | B6: Priya Kapoor | C6: Sr. Backend Engineer | D6: Core Backend | E6: Order/shipment lifecycle, business logic, Shopify sync, webhooks | F6: Order CRUD, shipment model, webhook processors, Shopify sync engine | G6: =COUNTIF('Data Models Gap'!I:I,"*PK*") -> 8 | H6: =COUNTIF('Feature Gap - Pages'!H:H,"*PK*") -> 0 | I6: =COUNTIF('Service & API Gap'!H:H,"*PK*") -> 10 | J6: =COUNTIF('Infrastructure Gap'!H:H,"*PK*") -> 1 | K6: =COUNTIF('Priority Roadmap'!I:I,"*PK*") -> 9 | L6: =SUM(G6:K6) -> 28
A7: VS | B7: Vikram Shah | C7: Backend Engineer | D7: Core Backend | E7: Route optimization, geospatial, carrier service, location mgmt | F7: PostGIS, route optimization, shipping profiles, delivery rules, carrier rates | G7: =COUNTIF('Data Models Gap'!I:I,"*VS*") -> 6 | H7: =COUNTIF('Feature Gap - Pages'!H:H,"*VS*") -> 1 | I7: =COUNTIF('Service & API Gap'!H:H,"*VS*") -> 12 | J7: =COUNTIF('Infrastructure Gap'!H:H,"*VS*") -> 0 | K7: =COUNTIF('Priority Roadmap'!I:I,"*VS*") -> 5 | L7: =SUM(G7:K7) -> 24
A8: NK | B8: Neha Krishnan | C8: Sr. Frontend Engineer | D8: Frontend | E8: Dashboard UI, design system, pages, components, UX | F8: Design system, dashboard pages, settings, analytics, onboarding | G8: =COUNTIF('Data Models Gap'!I:I,"*NK*") -> 1 | H8: =COUNTIF('Feature Gap - Pages'!H:H,"*NK*") -> 15 | I8: =COUNTIF('Service & API Gap'!H:H,"*NK*") -> 0 | J8: =COUNTIF('Infrastructure Gap'!H:H,"*NK*") -> 0 | K8: =COUNTIF('Priority Roadmap'!I:I,"*NK*") -> 1 | L8: =SUM(G8:K8) -> 17
A9: DM | B9: Dev Malhotra | C9: Frontend Engineer | D9: Frontend | E9: Order/shipment/route pages, map integrations, forms | F9: Order pages, shipment pages, route create/edit, zone map drawing, forms | G9: =COUNTIF('Data Models Gap'!I:I,"*DM*") -> 0 | H9: =COUNTIF('Feature Gap - Pages'!H:H,"*DM*") -> 15 | I9: =COUNTIF('Service & API Gap'!H:H,"*DM*") -> 0 | J9: =COUNTIF('Infrastructure Gap'!H:H,"*DM*") -> 1 | K9: =COUNTIF('Priority Roadmap'!I:I,"*DM*") -> 3 | L9: =SUM(G9:K9) -> 19
A10: SP | B10: Sanya Patel | C10: Full-Stack Engineer | D10: Integrations | E10: Notification providers, email/SMS/WhatsApp, Firebase push, templates | F10: SendGrid, Twilio, WhatsApp, FCM, notification templates, campaign system | G10: =COUNTIF('Data Models Gap'!I:I,"*SP*") -> 7 | H10: =COUNTIF('Feature Gap - Pages'!H:H,"*SP*") -> 3 | I10: =COUNTIF('Service & API Gap'!H:H,"*SP*") -> 7 | J10: =COUNTIF('Infrastructure Gap'!H:H,"*SP*") -> 4 | K10: =COUNTIF('Priority Roadmap'!I:I,"*SP*") -> 6 | L10: =SUM(G10:K10) -> 27
A11: RG | B11: Rohan Gupta | C11: Full-Stack Engineer | D11: Integrations | E11: Payment gateways, billing, analytics, 3rd-party APIs, super admin | F11: Payment module, billing/plans, analytics engine, cart plugin, POS | G11: =COUNTIF('Data Models Gap'!I:I,"*RG*") -> 9 | H11: =COUNTIF('Feature Gap - Pages'!H:H,"*RG*") -> 4 | I11: =COUNTIF('Service & API Gap'!H:H,"*RG*") -> 10 | J11: =COUNTIF('Infrastructure Gap'!H:H,"*RG*") -> 1 | K11: =COUNTIF('Priority Roadmap'!I:I,"*RG*") -> 5 | L11: =SUM(G11:K11) -> 29
A12: AM | B12: Aisha Mehra | C12: DevOps / Infra Engineer | D12: Platform | E12: Docker, CI/CD, Redis, BullMQ, PostGIS, monitoring, deployment | F12: Queue infrastructure, Redis caching, PostGIS setup, Docker, CI/CD, logging | G12: =COUNTIF('Data Models Gap'!I:I,"*AM*") -> 6 | H12: =COUNTIF('Feature Gap - Pages'!H:H,"*AM*") -> 0 | I12: =COUNTIF('Service & API Gap'!H:H,"*AM*") -> 8 | J12: =COUNTIF('Infrastructure Gap'!H:H,"*AM*") -> 13 | K12: =COUNTIF('Priority Roadmap'!I:I,"*AM*") -> 7 | L12: =SUM(G12:K12) -> 34
A13: KS | B13: Kabir Singh | C13: QA / Test Engineer | D13: Quality | E13: Test strategy, E2E tests, API tests, regression, data migration QA | F13: Test framework setup, API test suites, E2E scenarios, migration validation | G13: =COUNTIF('Data Models Gap'!I:I,"*KS*") -> 0 | H13: =COUNTIF('Feature Gap - Pages'!H:H,"*KS*") -> 0 | I13: =COUNTIF('Service & API Gap'!H:H,"*KS*") -> 0 | J13: =COUNTIF('Infrastructure Gap'!H:H,"*KS*") -> 1 | K13: =COUNTIF('Priority Roadmap'!I:I,"*KS*") -> 0 | L13: =SUM(G13:K13) -> 1
A14: TOTAL | G14: =SUM(G5:G13) -> 43 | H14: =SUM(H5:H13) -> 39 | I14: =SUM(I5:I13) -> 53 | J14: =SUM(J5:J13) -> 23 | K14: =SUM(K5:K13) -> 39 | L14: =SUM(L5:L13) -> 197
A16: Squad Structure
A17: Squad | B17: Members | C17: Primary Responsibility | D17: Phase Focus
A18: Architecture | B18: AR (Arjun) | C18: System design, auth, schema, cross-cutting concerns, code reviews | D18: Phase 1 lead, oversight all phases
A19: Core Backend | B19: PK (Priya), VS (Vikram) | C19: Order lifecycle, shipments, routes, shipping profiles, Shopify sync | D19: Phase 1-2 primary, Phase 4 support
A20: Frontend | B20: NK (Neha), DM (Dev) | C20: Dashboard UI, all pages, design system, map integrations, UX | D20: Phase 1-2 primary (parallel with backend)
A21: Integrations | B21: SP (Sanya), RG (Rohan) | C21: Notifications, payments, billing, analytics, 3rd-party APIs | D21: Phase 3-4 primary, Phase 5-6
A22: Platform | B22: AM (Aisha) | C22: Infrastructure, DevOps, queues, caching, monitoring, deployment | D22: Phase 1 setup, continuous throughout
A23: Quality | B23: KS (Kabir) | C23: Test strategy, automation, E2E, API tests, migration validation | D23: Continuous from Phase 2 onwards

Sheet Executive Summary
A1: WITYLOGIX PLATFORM — GAP ANALYSIS
A2: Old Backend (lmd-oms-v3 + lmd-oms-nextjs-v3) → New Platform (witylogix-platform)
A4: Last Updated: Sprint 2.6 (2026-03-07) | B4: Old System | C4: New Platform | D4: Gap
A5: Total Files: 555 source files | 168,753 lines of code | B5: 38+ | C5: 26 (Prisma) | D5: Consolidated into fewer, richer models
A6: Sprints Completed: 1.1, 1.2, 2.0, 2.1, 2.2, 2.3, 2.4, 2.5 | B6: 68 | C6: 50 | D6: Many features still need pages
A7: API Routes | B7: 85+ (Express) | C7: 42 (Fastify) | D7: Many endpoints still needed
A8: Services/Controllers | B8: 140+ / 80+ | C8: 7+ queue consumers | D8: Core business logic to rebuild
A9: Microservices (PM2) | B9: 12 | C9: 1 monolith + workers | D9: Queue workers needed
A10: Notification Channels | B10: Email, SMS, WhatsApp, Push, Slack | C10: Schema only | D10: All providers to integrate
A11: Payment Systems | B11: COD, Custom Gateways, Shopify Txn | C11: COD + gateway abstractions | D11: Stripe/Razorpay implementation needed
A12: Map Providers | B12: Google Maps + Mapbox | C12: Haversine + PostGIS spatial module | D12: PostGIS extension enable needed
A13: Webhook Processors | B13: 5 dedicated servers | C13: 4 webhook consumers | D13: Additional webhook types needed
A14: Real-time Tracking | B14: Firebase + WebSocket | C14: None | D14: Driver tracking to build
A15: Campaign/Marketing | B15: Email templates, Broadcasts | C15: None | D15: Campaign module needed
... A17: Components | B17: 296+ | C17: ~12 | D17: Component library to expand

Sheet Data Models Gap
A1: Old Model (MongoDB) | B1: Collection | C1: New Model (Prisma) | D1: Status | E1: Key Fields Missing in New | F1: Priority | G1: Notes | H1: Done | I1: Assignee | J1: Squad | K1: Work Status
A2: shopifyOrder | B2: shopify_orders | C2: Order | D2: EXISTS | E2: lineItems detail, billingAddress, shippingAddress, financialStatus, fulfillmentStatus, tags (rich), cancelledAt, refunds, discountCodes, taxLines, shippingLines, noteAttributes, orderRisk, orderSource | F2: P0 | G2: Core model - needs many Shopify-specific fields | H2: ☑ | I2: PK - Priya | J2: Core Backend | K2: DONE
A3: shipment | B3: shipments | C3: Shipment | D3: EXISTS | E3: Entire model: tracking_number, carrier, shipping_method, status lifecycle, label_url, customs_info, insurance, return_tracking, package_dimensions, weight, estimated_delivery_date, actual_delivery_date, shipping_cost, recipient_details, documents[], activity_log[] | F3: P0 | G3: Critical gap - old system had full shipment lifecycle separate from orders | H3: ☑ | I3: PK - Priya | J3: Core Backend | K3: DONE
A4: shipmentItem | B4: shipment_items | C4: ShipmentProof | D4: PARTIAL | E4: Entire model: shipment_ref, product_id, variant_id, quantity, weight, dimensions, customs_value, hs_code, origin_country | F4: P0 | G4: Needed for per-item shipment tracking | H4: ☐ | I4: PK - Priya | J4: Core Backend | K4: IN PROGRESS
A5: user | B5: users | C5: User | D5: EXISTS | E5: phone, avatar, permissions[], timezone, language, lastActiveAt, inviteToken, inviteExpiry, twoFactorEnabled, notificationPreferences | F5: P1 | G5: Old had richer user profiles | H5: ☑ | I5: AR - Arjun | J5: Architecture | K5: DONE
A6: userRole | B6: user_roles | C6: User.role (enum) | D6: EXISTS | E6: Full RBAC model with permissions array, resource-level access, customizable roles | F6: P1 | G6: Old had dynamic roles; new uses fixed enum | H6: ☑ | I6: AR - Arjun | J6: Architecture | K6: DONE
A7: userPermission | B7: user_permissions | C7: — | D7: MISSING | E7: Entire model: role_ref, resource, action, allow/deny, conditions | F7: P1 | G7: Granular permission system missing | H7: ☑ | I7: AR - Arjun | J7: Architecture | K7: DONE
A8: storeDetail | B8: store_details | C8: Shop | D8: EXISTS | E8: address, country, province, logo, favicon, social_links, business_hours, description, industry, defaultLanguage, supportEmail, returnPolicy, trackingPageConfig, widgetConfig, analyticsConfig | F8: P1 | G8: Shop model is minimal vs old storeDetail | H8: ☑ | I8: AR - Arjun | J8: Architecture | K8: DONE
A9: storeSettings | B9: store_settings | C9: Shop.settings (JSON) | D9: EXISTS | E9: Structured settings: autoAssign, proofOfDelivery, signatureRequired, realTimeTracking, driverAppConfig, customerNotificationDefaults, inventorySync, fulfillmentRules | F9: P1 | G9: Old had explicit fields; new uses opaque JSON | H9: ☑ | I9: AR - Arjun | J9: Architecture | K9: DONE
A10: storeApiSettings | B10: store_api_settings | C10: Integration | D10: EXISTS | E10: Old had dedicated model for API keys per provider (Google, Mapbox, Twilio, SendGrid, etc.) | F10: P2 | G10: Subsumed by Integration model but less explicit | H10: ☑ | I10: SP - Sanya | J10: Integrations | K10: DONE
A11: storeInfo | B11: store_infos | C11: Shop | D11: EXISTS | E11: Merged into Shop model | F11: — | G11: Consolidated correctly | H11: ☑ | I11: — | J11: — | K11: DONE
A12: calenderRule / calenderProfile | B12: calender_rules / calender_profiles | C12: — | D12: MISSING | E12: Entire models: blackout_dates[], operating_hours{}, preparation_time, cutoff_rules, holiday_calendars, recurring_rules, capacity_by_day, special_event_overrides | F12: P0 | G12: Sprint 2.5: calendar-engine.ts in shipping-profiles module | H12: ☑ | I12: VS - Vikram | J12: Core Backend | K12: DONE
... A40: billingSubscription | B40: billing_subscriptions | C40: Shop.planTier + billing routes | D40: PARTIAL | E40: Entire model: shop_ref, plan_ref, status, current_period_start, current_period_end, cancelled_at, shopify_charge_id | F40: P1 | G40: Subscription management missing | H40: ☐ | I40: RG - Rohan | J40: Integrations | K40: IN PROGRESS

Sheet Feature Gap - Pages
A1: Feature Area | B1: Old Frontend Page(s) | C1: New Dashboard Page | D1: Status | E1: Missing Capabilities | F1: Priority | G1: Done | H1: Assignee | I1: Squad | J1: Work Status
A2: Dashboard / Home | B2: home/index.js + fullAnalytics | C2: / | D2: EXISTS | E2: Real-time sync status, data syncing banner, video tutorials, Polaris Viz charts, feature timeline | F2: P1 | G2: ☑ | H2: NK - Neha | I2: Frontend | J2: DONE
A3: Orders List | B3: orders/index.js | C3: /orders + /orders/create + /orders/[id] + /orders/bulk + /orders/import | D3: EXISTS | E3: Map view (Leaflet), CSV import modal, bulk actions, advanced filter presets, saved views | F3: P0 | G3: ☑ | H3: DM - Dev | I3: Frontend | J3: DONE
A4: Order Creation | B4: create-order/index.js | C4: /orders/create | D4: EXISTS | E4: Manual order creation form: customer details, line items, address, time slot, payment method, notes | F4: P0 | G4: ☑ | H4: DM - Dev | I4: Frontend | J4: DONE
A5: Order Details | B5: order-details/[...slug].js | C5: /orders/[id] | D5: EXISTS | E5: Full page view, shipment-in-order view, price breakdown, order tags editor, fulfillment actions, refund actions | F5: P0 | G5: ☑ | H5: DM - Dev | I5: Frontend | J5: DONE
A6: Shipments List | B6: shipments/index.js + local-delivery/shipments + store-pickup/shipments + standard-delivery/shipments | C6: /shipments | D6: EXISTS | E6: Entire shipment management: list, filters, map view, status tracking, bulk operations, multi-delivery-method views | F6: P0 | G6: ☑ | H6: DM - Dev | I6: Frontend | J6: DONE
A7: Shipment Details | B7: shipment-details/index.js + variants | C7: — | D7: EXISTS | E7: Full shipment detail: items, price breakdown, documents/POD, tracking notes, SMS confirmation, payment transactions, more actions | Sprint 2.4 - Shipment detail page | F7: P0 | G7: ☑ | H7: DM - Dev | I7: Frontend | J7: DONE
A8: Local Delivery Orders | B8: local-delivery/orders/index.js | C8: /orders/local | D8: EXISTS | E8: Delivery-method-specific order views with method-specific filters and actions | F8: P1 | G8: ☑ | H8: DM - Dev | I8: Frontend | J8: DONE
A9: Store Pickup | B9: store-pickup/* (4 pages) | C9: — | D9: EXISTS | E9: Store pickup workflow: orders, shipments, details, ready-for-pickup actions | Sprint 2.4 - Multi-store management | F9: P1 | G9: ☑ | H9: DM - Dev | I9: Frontend | J9: DONE
A10: Standard Delivery | B10: standard-delivery/* (4 pages) | C10: — | D10: MISSING | E10: Standard shipping workflow: orders, shipments, details, carrier assignment | F10: P1 | G10: ☐ | H10: DM - Dev | I10: Frontend | J10: NOT STARTED
A11: Routes List | B11: local-delivery/routes/index.js + routes/index.js | C11: /routes + /routes/create + /routes/[id] + /routes/[id]/edit | D11: EXISTS | E11: Route table pagination, search, timeline view, shipping label printing (4x6), CSV export, route claiming | F11: P0 | G11: ☑ | H11: NK - Neha | I11: Frontend | J11: DONE
A12: Route Create | B12: routes/create/index.js | C12: /routes/create | D12: EXISTS | E12: Route creation wizard: select shipments, assign driver, set start/end location, drag-and-drop ordering, map preview | F12: P0 | G12: ☑ | H12: DM - Dev | I12: Frontend | J12: DONE
... A40: Notifications | B40: — (none) | C40: /notifications | D40: EXISTS | E40: Notification center | F40: P2 | G40: ☑ | H40: SP | I40: Integrations | J40: DONE

Sheet Service & API Gap
A1: Service Domain | B1: Old Services (lmd-oms-v3) | C1: New API Routes (Fastify) | D1: Status | E1: Key Endpoints Missing | F1: Priority | G1: Done | H1: Assignee | I1: Squad | J1: Work Status
A2: Authentication | B2: users/userService (JWT + cookie sessions) | C2: routes/auth.ts | D2: EXISTS | E2: Google OAuth, password reset flow, email verification, 2FA, refresh token rotation, session management | F2: P0 | G2: ☑ | H2: AR - Arjun | I2: Architecture | J2: DONE
A3: Order CRUD | B3: orders/orderService + orderCountService | C3: routes/orders.ts | D3: EXISTS | E3: Manual order creation, order import (CSV), bulk status update, order merge/split, refund initiation, fulfillment creation | F3: P0 | G3: ☑ | H3: PK - Priya | I3: Core Backend | J3: DONE
A4: Shipment Lifecycle | B4: shipment/* (18 service files) | C4: — | D4: EXISTS | E4: Entire shipment domain: create from order, status transitions, assign to route, label generation, tracking updates, documents, payment tracking, activity log | F4: Sprint 2.4 - FileStorage (local + S3) | G4: ☑ | H4: PK - Priya | I4: Core Backend | J4: DONE
A5: Route Optimization | B5: serviceBus/mapbox + locationService/mapboxService + googleMapService | C5: packages/core/src/route-optimizer/ (5 files) | D5: EXISTS | E5: Nearest-neighbor, 2-opt, Clarke-Wright algorithms; ETA calculation; distance matrix | F5: P0 | G5: ☑ | H5: VS - Vikram | I5: Core Backend | J5: DONE
A6: Route Management | B6: shipment/shipmentRoutes + shipmentRouteDirection | C6: routes/routes.ts | D6: EXISTS | E6: Route CRUD exists but missing: optimization integration, direction rendering, stop reordering, driver notification on assignment, route claiming, label printing | F6: P0 | G6: ☑ | H6: VS - Vikram | I6: Core Backend | J6: DONE
A7: Location/Warehouse Mgmt | B7: — (via storeDetail) | C7: routes/locations-v2.ts (13 endpoints) | D7: EXISTS | E7: Working hours, capacity, zone associations, nearest location (Haversine) | F7: P0 | G7: ☑ | H7: VS - Vikram | I7: Core Backend | J7: DONE
A8: Shipping Profiles | B8: profiles/shippingProfile + calenderProfile | C8: — | D8: EXISTS | E8: Rate calculation engine, calendar rules, delivery windows, processing times, conditional rules, zone-based pricing | F8: Sprint 2.4 - FileStorage (local + S3) | G8: ☑ | H8: VS - Vikram | I8: Core Backend | J8: DONE
A9: Delivery Rules Engine | B9: shipment/shipmentRules + calenderRules/* | C9: — | D9: EXISTS | E9: Distance-based, weight-based, zone-based, time-based, product-category rules; min order; same-day/next-day logic | F9: Sprint 2.4 - Delivery rules engine | G9: ☑ | H9: VS - Vikram | I9: Core Backend | J9: DONE
A10: Carrier Rate Calculation | B10: carrierService/* (6 files) | C10: routes/carriers.ts | D10: EXISTS | E10: Rate calculator engine, natural load balancing, Shopify carrier service callback, multi-carrier comparison | F10: Sprint 2.4 - FileStorage (local + S3) | G10: ☑ | H10: VS - Vikram | I10: Core Backend | J10: DONE
A11: Notification Dispatch | B11: notifications/* (9 files) | C11: — | D11: EXISTS | E11: Email (SendGrid/SMTP), SMS (Twilio), WhatsApp (Meta Cloud API), Push (Firebase), Slack — all channel dispatchers | F11: Sprint 2.4 - FileStorage (local + S3) | G11: ☑ | H11: SP - Sanya | I11: Integrations | J11: DONE
A12: Notification Templates | B12: campaign/emailTemplate + whatsappTemplate | C12: — | D12: EXISTS | E12: Template CRUD, Unlayer email editor, WhatsApp template sync, variable interpolation, multi-language | F12: Sprint 2.4 - Campaign manager + template engine | G12: ☑ | H12: SP - Sanya | I12: Integrations | J12: DONE
... A51: Health Checks | B51: — (none) | C51: routes/health.ts | D51: EXISTS | E51: — (liveness + readiness + deep) | F51: P1 | G51: ☑ | H51: RG | I51: Backend | J51: DONE

Sheet Infrastructure Gap
A1: Component | B1: Old System | C1: New Platform | D1: Status | E1: Action Required | F1: Priority | G1: Done | H1: Assignee | I1: Squad | J1: Work Status
A2: Database | B2: MongoDB (Mongoose + speed-goose caching) | C2: PostgreSQL + Prisma 6 | D2: EXISTS | E2: Data migration scripts needed for existing customers | F2: P0 | G2: ☑ | H2: AM - Aisha | I2: Platform | J2: DONE
A3: Message Queue | B3: Azure Service Bus (9 queues) | C3: packages/core/src/queue/ (7 consumers + base class) | D3: EXISTS | E3: BullMQ consumers: order-webhook, product-webhook, driver-tracking, event-scheduler + DLQ | F3: P0 | G3: ☑ | H3: AM - Aisha | I3: Platform | J3: DONE
A4: Cache Layer | B4: Redis (sessions + pub/sub + ORM cache) | C4: packages/core/src/cache/ | D4: EXISTS | E4: Redis client exists but caching strategy not implemented; need: session store, query cache, rate limiting, pub/sub for real-time | F4: P1 | G4: ☑ | H4: AM - Aisha | I4: Platform | J4: DONE
A5: Real-time | B5: Firebase Realtime Database + WebSocket | C5: Socket.io realtime layer | D5: EXISTS | E5: Need real-time infrastructure: WebSocket/SSE server, driver location streaming, order status push to customers | F5: P0 | G5: ☑ | H5: AM - Aisha | I5: Platform | J5: DONE
A6: File Storage | B6: Local + cloud (implied) | C6: — | D6: EXISTS | E6: Sprint 2.4 - Local + S3 file storage | F6: P1 | G6: ☑ | H6: AM - Aisha | I6: Platform | J6: DONE
A7: Process Manager | B7: PM2 (12 processes) | C7: Single Fastify + BullMQ workers | D7: REDESIGNED | E7: Workers exist as stubs; need full implementations | F7: P1 | G7: ☐ | H7: AM - Aisha | I7: Platform | J7: NOT STARTED
A8: Geospatial | B8: Google Maps + Mapbox APIs | C8: geo-fence.ts + address.ts | D8: EXISTS | E8: Re-enable PostGIS, implement geocoding service, distance matrix, route optimization API | F8: P0 | G8: ☑ | H8: AM - Aisha | I8: Platform | J8: DONE
A9: Email Provider | B9: SendGrid / SMTP (via notification service) | C9: email/providers + dispatch | D9: EXISTS | E9: Email sending integration, template rendering, delivery tracking | F9: P0 | G9: ☑ | H9: SP - Sanya | I9: Integrations | J9: DONE
A10: SMS Provider | B10: Twilio (via smsService) | C10: sms/providers + dispatch | D10: EXISTS | E10: SMS sending, delivery receipts, phone number validation | F10: P1 | G10: ☑ | H10: SP - Sanya | I10: Integrations | J10: DONE
A11: WhatsApp | B11: Meta Cloud API (via whatsApp services) | C11: — | D11: MISSING | E11: WhatsApp Business API: template management, message sending, webhook handling | F11: P1 | G11: ☑ | H11: SP - Sanya | I11: Integrations | J11: DONE
A12: Push Notifications | B12: Firebase Cloud Messaging | C12: push-handler.ts (FCM) | D12: PARTIAL | E12: FCM integration for driver app push notifications | F12: P1 | G12: ☑ | H12: SP - Sanya | I12: Integrations | J12: DONE
... A24: E2E Test Suites | B24: — (none) | C24: 7 test files (4,439 lines) | D24: EXISTS | E24: — (compliance, cache, API tests) | F24: P2 | G24: ☑ | H24: KS | I24: QA | J24: DONE

Sheet Priority Roadmap
A1: Phase | B1: Sprint | C1: Work Item | D1: Category | E1: Est. Effort | F1: Dependencies | G1: Deliverable | H1: Done | I1: Assignee | J1: Squad | K1: Work Status
A2: Phase 1: Foundation | B2: 1-2 | C2: Authentication system (JWT, login, register, password reset) | D2: Backend + Frontend | E2: 2 weeks | F2: — | G2: Auth middleware, login/register pages, session management | H2: ☑ | I2: AR - Arjun | J2: Architecture | K2: DONE
A3: Phase 1: Foundation | B3: 1-2 | C3: PostGIS re-enable + geocoding service | D3: Backend + Infra | E3: 1 week | F3: — | G3: Spatial queries, point-in-polygon, distance calc | H3: ☑ | I3: AM - Aisha | J3: Platform | K3: DONE
A4: Phase 1: Foundation | B4: 1-2 | C4: Shipment model + migration | D4: Backend | E4: 1 week | F4: — | G4: Prisma schema + API routes for shipments | H4: ☑ | I4: PK - Priya | J4: Core Backend | K4: DONE
A5: Phase 1: Foundation | B5: 2-3 | C5: Location/Warehouse model + CRUD | D5: Backend + Frontend | E5: 2 weeks | F5: PostGIS | G5: Location management pages + API | H5: ☑ | I5: VS - Vikram | J5: Core Backend | K5: DONE
A6: Phase 1: Foundation | B6: 2-3 | C6: Calendar rules + delivery rules engine | D6: Backend | E6: 2 weeks | F6: — | G6: Scheduling engine, blackout dates, time windows | H6: ☑ | I6: VS - Vikram | J6: Core Backend | K6: DONE
A7: Phase 1: Foundation | B7: 3-4 | C7: Shipping profile system | D7: Backend + Frontend | E7: 2 weeks | F7: Locations, Zones, Rules | G7: Rate calculation, profile management UI | H7: ☑ | I7: VS - Vikram | J7: Core Backend | K7: DONE
A8: Phase 2: Core Ops | B8: 5-6 | C8: Order CRUD (full lifecycle + manual creation) | D8: Backend + Frontend | E8: 2 weeks | F8: Auth | G8: Order create page, detail page, status management | H8: ☑ | I8: PK - Priya | J8: Core Backend | K8: DONE
A9: Phase 2: Core Ops | B9: 5-6 | C9: Shipment lifecycle (create, track, deliver) | D9: Backend + Frontend | E9: 3 weeks | F9: Shipment model, Orders | G9: Shipment pages, status transitions, POD | H9: ☑ | I9: PK - Priya | J9: Core Backend | K9: DONE
A10: Phase 2: Core Ops | B10: 6-7 | C10: Route optimization (Mapbox/Google integration) | D10: Backend | E10: 2 weeks | F10: PostGIS, Drivers | G10: Distance matrix, route optimization API | H10: ☑ | I10: VS - Vikram | J10: Core Backend | K10: DONE
A11: Phase 2: Core Ops | B11: 7-8 | C11: Route creation + editing UI | D11: Frontend | E11: 2 weeks | F11: Route optimization | G11: Route create/edit pages with map + drag/drop | H11: ☑ | I11: DM - Dev | J11: Frontend | K11: DONE
A12: Phase 2: Core Ops | B12: 7-8 | C12: Webhook processing (order, product, customer, inventory) | D12: Backend | E12: 2 weeks | F12: BullMQ | G12: Queue consumers for each Shopify webhook type | H12: ☑ | I12: PK - Priya | J12: Core Backend | K12: DONE
... A36: Phase 6: Polish | B36: 24-25 | C36: CI/CD, Docker, monitoring | D36: Infra | E36: 2 weeks | F36: — | G36: Docker builds, Sentry, Pino logging, deployment | H36: ☑ | I36: AM - Aisha | J36: Platform | K36: DONE

Sheet Statistics
A1: Gap Statistics Summary
A3: SPRINT PROGRESS (as of Sprint 2.6)
A4: Last Updated: Sprint 2.6 (2026-03-07)
A5: Metric | B5: Sprint 1.1 | C5: Sprint 1.2 | D5: Sprint 2.0 | E5: Sprint 2.1 | F5: Sprint 2.3 | G5: Sprint 2.4 | H5: Sprint 2.5 | I5: Sprint 2.6
A6: Source Files | B6: 184 | C6: 258 | D6: 325 | E6: 418 | F6: 429 | G6: 461 | H6: 512 | I6: 555
A7: Lines of Code | B7: 22541 | C7: 40672 | D7: 58339 | E7: 83232 | F7: 113346 | G7: 130966 | H7: 153011 | I7: 168753
A8: Dashboard Pages | B8: 10 | C8: 14 | D8: 18 | E8: 24 | F8: 37 | G8: 47 | H8: 50 | I8: 50
A9: API Routes | B9: 8 | C9: 12 | D9: 18 | E9: 25 | F9: 27 | G9: 39 | H9: 42 | I9: 44
A10: Prisma Models | B10: 18 | C10: 22 | D10: 26 | E10: 30 | F10: 32 | G10: 34 | H10: 26 | I10: 25
A11: Core Modules | B11: 4 | C11: 6 | D11: 8 | E11: 12 | F11: 18 | G11: 32 | H11: 38 | I11: 43
A12: Test Files | B12: 0 | C12: 0 | D12: 0 | E12: 0 | F12: 22 | G12: 29 | H12: 37 | I12: 44
A14: SPRINT 2.5 DELIVERABLES
A16: Agent | B16: Deliverable | C16: Files | D16: Lines | E16: Status
A17: AR - Arjun | B17: Route optimization engine (3 algorithms + ETA) | C17: 7 | D17: 1610 | E17: DONE
A18: DM - Dev | B18: Shipping profiles detail, route assign, local orders pages | C18: 3 | D18: 1572 | E18: DONE
A19: NK - Neha | B19: Cart plugin components (date picker, time slots, rates) | C19: 5 | D19: 1817 | E19: DONE
A20: RG - Rohan | B20: Queue consumers (4 types) + spatial queries module | C20: 10 | D20: 3813 | E20: DONE
A21: SP - Sanya | B21: Payment processing (gateway + processor + Prisma) | C21: 6 | D21: 2689 | E21: DONE
A22: VS - Vikram | B22: Shipping profiles core (rate calc, calendar, validator) | C22: 6 | D22: 3068 | E22: DONE
A23: PK - Priya | B23: Analytics engine (event tracker, aggregator, dashboard) | C23: 6 | D23: 2275 | E23: DONE
A24: KS - Kavitha | B24: 8 test suites (optimizer, payments, analytics, queue, etc.) | C24: 8 | D24: 5184 | E24: DONE
A25: AM - Aisha | B25: Migration framework + location management API | C25: 5 | D25: 1914 | E25: DONE
A27: SPRINT 2.6 DELIVERABLES
A36: PK - Priya | B36: Campaign, messaging, audit, permissions API routes | C36: 4 | D36: 2469 | E36: DONE
A37: KS - Kavitha | B37: 7 test suites (RBAC, audit, dispatcher, crypto, etc.) | C37: 7 | D37: 4725 | E37: DONE
A38: AM - Aisha | B38: Shopify campaigns, templates, audit log routes | C38: 5 | D38: 1628 | E38: DONE
A41: COMPLETION SUMMARY
A42: Category | B42: Total Items | C42: Done | D42: In Progress | E42: Remaining | F42: % Complete
A43: Data Models | B43: 39 | C43: 26 | D43: 3 | E43: =B43-C43-D43 -> 10 | F43: =C43/B43 -> 0.66666667
A44: Feature Pages | B44: 34 | C44: 28 | D44: 0 | E44: =B44-C44-D44 -> 6 | F44: =C44/B44 -> 0.82352941
A45: API Services | B45: 34 | C45: 34 | D45: 0 | E45: =B45-C45-D45 -> 0 | F45: =C45/B45 -> 1
A46: Infrastructure | B46: 21 | C46: 15 | D46: 0 | E46: =B46-C46-D46 -> 6 | F46: =C46/B46 -> 0.71428571
A47: Roadmap Items | B47: 35 | C47: 25 | D47: 2 | E47: =B47-C47-D47 -> 8 | F47: =C47/B47 -> 0.71428571
