Workbook

Sheet Team Directory
A1: WITYLOGIX — STARTUP ENGINEERING TEAM
A2: 9-person team organized into 5 squads — working in parallel across 6 phases
A4: ID | B4: Name | C4: Role | D4: Squad | E4: Focus Areas | F4: Parallel Tracks | G4: Models | H4: Pages | I4: Services | J4: Infra | K4: Roadmap | L4: Total Items
A5: AR | B5: Arjun Rajput | C5: CTO / Tech Lead | D5: Architecture | E5: System design, API architecture, DB schema, auth, infra decisions | F5: Auth system, RBAC, schema design, code reviews | G5: =COUNTIF('Data Models Gap'!I:I,"*AR*") | H5: =COUNTIF('Feature Gap - Pages'!H:H,"*AR*") | I5: =COUNTIF('Service & API Gap'!H:H,"*AR*") | J5: =COUNTIF('Infrastructure Gap'!H:H,"*AR*") | K5: =COUNTIF('Priority Roadmap'!I:I,"*AR*") | L5: =SUM(G5:K5)
A6: PK | B6: Priya Kapoor | C6: Sr. Backend Engineer | D6: Core Backend | E6: Order/shipment lifecycle, business logic, Shopify sync, webhooks | F6: Order CRUD, shipment model, webhook processors, Shopify sync engine | G6: =COUNTIF('Data Models Gap'!I:I,"*PK*") | H6: =COUNTIF('Feature Gap - Pages'!H:H,"*PK*") | I6: =COUNTIF('Service & API Gap'!H:H,"*PK*") | J6: =COUNTIF('Infrastructure Gap'!H:H,"*PK*") | K6: =COUNTIF('Priority Roadmap'!I:I,"*PK*") | L6: =SUM(G6:K6)
A7: VS | B7: Vikram Shah | C7: Backend Engineer | D7: Core Backend | E7: Route optimization, geospatial, carrier service, location mgmt | F7: PostGIS, route optimization, shipping profiles, delivery rules, carrier rates | G7: =COUNTIF('Data Models Gap'!I:I,"*VS*") | H7: =COUNTIF('Feature Gap - Pages'!H:H,"*VS*") | I7: =COUNTIF('Service & API Gap'!H:H,"*VS*") | J7: =COUNTIF('Infrastructure Gap'!H:H,"*VS*") | K7: =COUNTIF('Priority Roadmap'!I:I,"*VS*") | L7: =SUM(G7:K7)
A8: NK | B8: Neha Krishnan | C8: Sr. Frontend Engineer | D8: Frontend | E8: Dashboard UI, design system, pages, components, UX | F8: Design system, dashboard pages, settings, analytics, onboarding | G8: =COUNTIF('Data Models Gap'!I:I,"*NK*") | H8: =COUNTIF('Feature Gap - Pages'!H:H,"*NK*") | I8: =COUNTIF('Service & API Gap'!H:H,"*NK*") | J8: =COUNTIF('Infrastructure Gap'!H:H,"*NK*") | K8: =COUNTIF('Priority Roadmap'!I:I,"*NK*") | L8: =SUM(G8:K8)
A9: DM | B9: Dev Malhotra | C9: Frontend Engineer | D9: Frontend | E9: Order/shipment/route pages, map integrations, forms | F9: Order pages, shipment pages, route create/edit, zone map drawing, forms | G9: =COUNTIF('Data Models Gap'!I:I,"*DM*") | H9: =COUNTIF('Feature Gap - Pages'!H:H,"*DM*") | I9: =COUNTIF('Service & API Gap'!H:H,"*DM*") | J9: =COUNTIF('Infrastructure Gap'!H:H,"*DM*") | K9: =COUNTIF('Priority Roadmap'!I:I,"*DM*") | L9: =SUM(G9:K9)
A10: SP | B10: Sanya Patel | C10: Full-Stack Engineer | D10: Integrations | E10: Notification providers, email/SMS/WhatsApp, Firebase push, templates | F10: SendGrid, Twilio, WhatsApp, FCM, notification templates, campaign system | G10: =COUNTIF('Data Models Gap'!I:I,"*SP*") | H10: =COUNTIF('Feature Gap - Pages'!H:H,"*SP*") | I10: =COUNTIF('Service & API Gap'!H:H,"*SP*") | J10: =COUNTIF('Infrastructure Gap'!H:H,"*SP*") | K10: =COUNTIF('Priority Roadmap'!I:I,"*SP*") | L10: =SUM(G10:K10)
A11: RG | B11: Rohan Gupta | C11: Full-Stack Engineer | D11: Integrations | E11: Payment gateways, billing, analytics, 3rd-party APIs, super admin | F11: Payment module, billing/plans, analytics engine, cart plugin, POS | G11: =COUNTIF('Data Models Gap'!I:I,"*RG*") | H11: =COUNTIF('Feature Gap - Pages'!H:H,"*RG*") | I11: =COUNTIF('Service & API Gap'!H:H,"*RG*") | J11: =COUNTIF('Infrastructure Gap'!H:H,"*RG*") | K11: =COUNTIF('Priority Roadmap'!I:I,"*RG*") | L11: =SUM(G11:K11)
A12: AM | B12: Aisha Mehra | C12: DevOps / Infra Engineer | D12: Platform | E12: Docker, CI/CD, Redis, BullMQ, PostGIS, monitoring, deployment | F12: Queue infrastructure, Redis caching, PostGIS setup, Docker, CI/CD, logging | G12: =COUNTIF('Data Models Gap'!I:I,"*AM*") | H12: =COUNTIF('Feature Gap - Pages'!H:H,"*AM*") | I12: =COUNTIF('Service & API Gap'!H:H,"*AM*") | J12: =COUNTIF('Infrastructure Gap'!H:H,"*AM*") | K12: =COUNTIF('Priority Roadmap'!I:I,"*AM*") | L12: =SUM(G12:K12)
A13: KS | B13: Kabir Singh | C13: QA / Test Engineer | D13: Quality | E13: Test strategy, E2E tests, API tests, regression, data migration QA | F13: Test framework setup, API test suites, E2E scenarios, migration validation | G13: =COUNTIF('Data Models Gap'!I:I,"*KS*") | H13: =COUNTIF('Feature Gap - Pages'!H:H,"*KS*") | I13: =COUNTIF('Service & API Gap'!H:H,"*KS*") | J13: =COUNTIF('Infrastructure Gap'!H:H,"*KS*") | K13: =COUNTIF('Priority Roadmap'!I:I,"*KS*") | L13: =SUM(G13:K13)
A14: TOTAL | G14: =SUM(G5:G13) | H14: =SUM(H5:H13) | I14: =SUM(I5:I13) | J14: =SUM(J5:J13) | K14: =SUM(K5:K13) | L14: =SUM(L5:L13)
A16: Squad Structure
A17: Squad | B17: Members | C17: Primary Responsibility | D17: Phase Focus
A18: Architecture | B18: AR (Arjun) | C18: System design, auth, schema, cross-cutting concerns, code reviews | D18: Phase 1 lead, oversight all phases
A19: Core Backend | B19: PK (Priya), VS (Vikram) | C19: Order lifecycle, shipments, routes, shipping profiles, Shopify sync | D19: Phase 1-2 primary, Phase 4 support
A20: Frontend | B20: NK (Neha), DM (Dev) | C20: Dashboard UI, all pages, design system, map integrations, UX | D20: Phase 1-2 primary (parallel with backend)
A21: Integrations | B21: SP (Sanya), RG (Rohan) | C21: Notifications, payments, billing, analytics, 3rd-party APIs | D21: Phase 3-4 primary, Phase 5-6
A22: Platform | B22: AM (Aisha) | C22: Infrastructure, DevOps, queues, caching, monitoring, deployment | D22: Phase 1 setup, continuous throughout
A23: Quality | B23: KS (Kabir) | C23: Test strategy, automation, E2E, API tests, migration validation | D23: Continuous from Phase 2 onwards

Sheet Sprint 4.6 Plan (Done)
A1: Agent | B1: Role | C1: Task | D1: Files/Packages | E1: Key Deliverables | F1: Gap Ref | G1: Status
A2: AR - Arjun | B2: CTO | C2: Planned-vs-Actual Analytics Dashboard + ADR-025 | D2: docs/adr/ADR-025-*.md, apps/dashboard/src/app/(dashboard)/analytics/* | E2: Route analytics page, on-time %, driver scorecard, CO2 estimates, planned-vs-actual comparison, trend charts | F2: G-10 | G2: TODO
A3: DM - Deepak | B3: Frontend | C3: Customer Portal v2 — Real-Time Tracking + Maps | D3: apps/customer-portal/src/app/track/*, apps/customer-portal/src/components/live-map.tsx | E3: Live WebSocket tracking, Leaflet map with driver position, ETA countdown, mobile-responsive polish, delivery history | F3: — | G3: TODO
A4: NK - Nikhil | B4: Frontend Lead | C4: Google Maps Native UI Components | D4: packages/ui/src/maps/*, apps/dashboard/src/components/maps/* | E4: Address autocomplete, zone map visualization, embedded route map, draggable zone polygon editor, place search | F4: G-09 | G4: TODO
A5: RG - Rahul | B5: Backend Lead | C5: WooCommerce REST API Adapter | D5: packages/core/src/integrations/woocommerce/*, apps/api/src/routes/integrations/woocommerce.ts | E5: Order sync (create/update/delete), product sync, customer sync, webhook consumer, WC REST v3 client, retry logic | F5: G-08 | G5: TODO
A6: SP - Sanjay | B6: Full-stack | C6: Notification Preferences UI + WhatsApp Templates | D6: apps/dashboard/src/app/(dashboard)/notifications/*, packages/core/src/notifications-v2/templates/* | E6: Dashboard notification settings page, per-tenant channel config, WhatsApp template CRUD, delivery notification preview, test send | F6: G-06 | G6: TODO
A7: VS - Vikram | B7: Component Dev | C7: Analytics Chart Components + KPI Library | D7: apps/dashboard/src/components/analytics/*, apps/dashboard/src/components/ui/chart-*.tsx | E7: Line chart, bar chart, pie chart, heatmap, KPI card, comparison card, sparkline, chart tooltip, responsive containers | F7: — | G7: TODO
A8: PK - Priya | B8: Sr. Backend | C8: Invoice Engine Foundation | D8: packages/core/src/invoicing/*, packages/db/prisma/schema/45-invoices.prisma, apps/api/src/routes/invoices.ts | E8: Invoice model (8+ fields), per-delivery cost calc, PDF generation (pdfkit), invoice API (CRUD + send), Prisma schema | F8: G-13 | G8: TODO
A9: KS - Kavitha | B9: QA Lead | C9: Integration Tests + Sprint 4.5 Unit Tests | D9: tests/e2e/specs/integrations/*, tests/unit/woocommerce/*, tests/unit/analytics/* | E9: WooCommerce adapter tests, analytics API tests, notification integration tests, POD unit tests, invoice API tests | F9: — | G9: TODO
A10: AM - Aisha | B10: Integration | C10: WooCommerce Checkout Block + Platform Bridge | D10: extensions/woocommerce-block/*, packages/core/src/integrations/woocommerce/checkout-block.ts | E10: WC checkout block extension, delivery date picker for WC, Shopify-WC data normalizer, webhook normalization layer | F10: G-08 | G10: TODO
A11: ZR - Zara | B11: AI Engineer | C11: Route Analytics ML — Efficiency & Prediction | D11: packages/core/src/ai-analytics/*, apps/api/src/routes/ai/analytics.ts | E11: Route efficiency scoring model, driver performance ML, delivery time prediction refinement, route anomaly detection, API endpoints | F11: G-10 | G11: TODO
A13: THEME | B13: Sprint 4.6 — Integrations, Analytics & Platform Maturity
A14: GAP TARGETS | B14: G-08 (WooCommerce), G-09 (Google Maps Native), G-10 (Planned-vs-Actual), G-13 (Invoice start)

Sheet Executive Summary
A1: WITYLOGIX PLATFORM — GAP ANALYSIS
A2: Old Backend (lmd-oms-v3 + lmd-oms-nextjs-v3) → New Platform (witylogix-platform)
A4: Last Updated: Sprint 3.0 (2026-03-08) | B4: Old System | C4: New Platform | D4: Gap
A5: Total Files: 555 source files | 168,753 lines of code | B5: 38+ | C5: 26 (Prisma) | D5: Consolidated into fewer, richer models
A6: Sprints Completed: 1.1, 1.2, 2.0, 2.1, 2.2, 2.3, 2.4, 2.5 | B6: 68 | C6: 50 | D6: Many features still need pages
A7: API Routes | B7: 85+ (Express) | C7: 42 (Fastify) | D7: Many endpoints still needed
A8: Services/Controllers | B8: 140+ / 80+ | C8: 7+ queue consumers | D8: Core business logic to rebuild
A9: Microservices (PM2) | B9: 12 | C9: 1 monolith + workers | D9: Queue workers needed
A10: Notification Channels | B10: Email, SMS, WhatsApp, Push, Slack | C10: Schema only | D10: All providers to integrate
A11: Payment Systems | B11: COD, Custom Gateways, Shopify Txn | C11: COD + gateway abstractions | D11: Stripe/Razorpay implementation needed
A12: Map Providers | B12: Google Maps + Mapbox | C12: Haversine + PostGIS spatial module | D12: PostGIS extension enable needed
A13: Webhook Processors | B13: 5 dedicated servers | C13: 4 webhook consumers | D13: Additional webhook types needed
A14: Real-time Tracking | B14: Firebase + WebSocket | C14: None | D14: Driver tracking to build
A15: Campaign/Marketing | B15: Email templates, Broadcasts | C15: None | D15: Campaign module needed
... A17: Components | B17: 296+ | C17: ~12 | D17: Component library to expand

Sheet Competitive Gap Tracker
A1: ID | B1: Priority | C1: Gap Item | D1: Description | E1: Effort | F1: Competitive Leader | G1: Sprint Target | H1: Agent(s) | I1: Status | J1: Notes
A2: G-01 | B2: P0 | C2: Customer Self-Service Portal | D2: Build a full customer portal app (Next.js): order history with delivery status timeline, live GPS tracking on map, rescheduling flow (select new date/slot), delivery preferences (safe place instructions, preferred times, access codes), driver rating system, notification preference management. Currently ABSENT in all 6 competitors except Route4Me — massive first-mover opportunity for open-source. Reference: Route4Me has basic portal with order tracking + rescheduling. | E2: L | F2: Route4Me (only one) | G2: 4.5 | H2: DM | I2: PLANNED | J2: New app: apps/customer-portal/. React + Next.js. Auth via existing session manager.
A3: G-02 | B3: P0 | C3: Checkout Date/Time Picker Widget | D3: Build an embeddable checkout widget matching Pickeasy quality: date calendar with availability indicators, time slot grid showing remaining capacity per slot, zone-based delivery rate display, blackout date configuration, order cut-off/deadline engine (e.g. 'Friday pickup must be scheduled by Thursday 4pm'), zipcode/postcode validation with Google Maps, preparation time settings, product-specific delivery rules. Pickeasy has 8K+ merchants, 4.9 stars — this is the benchmark. ScrollEngine and Zapiet also strong here. | E3: M | F3: Pickeasy / ScrollEngine / Zapiet | G3: 4.5 | H3: NK, VS | I3: PLANNED | J3: Package: packages/checkout-widget/. Must be embeddable in Shopify, WooCommerce, standalone.
A4: G-03 | B4: P0 | C4: POD Enhancement (Photo + Signature + QR + Timeline) | D4: Upgrade proof-of-delivery to match Fleetbase + Routific: multi-method capture (photo of delivery at doorstep, e-signature pad, QR code scan, barcode verification), delivery status timeline UI (Planned → Out for Delivery → Delivered with timestamp + photo attachment), S3/R2 cloud storage for POD media, offline-capable POD capture that syncs when back online. Routific shows excellent UX with status timeline + photo proof. Fleetbase has QR + signature + manual methods. | E4: M | F4: Fleetbase + Routific | G4: 4.5 | H4: PK | I4: PLANNED | J4: packages/core/src/pod/. Driver app integration. Status timeline component for tracking page.
A5: G-04 | B5: P0 | C5: Route Timeline Dispatcher Dashboard | D5: Build Routific-quality dispatcher dashboard: interactive map showing color-coded routes per driver (10+ colors), timeline/Gantt view (8am-7pm) with stop dots per route, unscheduled vs scheduled orders toggle, real-time stats bar (active drivers, total stops, total km, estimated time), drag-and-drop route editing to reassign stops between drivers, 'Plan Routes' one-click optimization button. Reference: Routific screenshot shows 10 routes, 540 stops, 1200km, 65h 15m. | E5: L | F5: Routific | G5: 4.5 | H5: AR | I5: PLANNED | J5: apps/dashboard/src/app/(dashboard)/dispatch/. Uses Mapbox/Leaflet + D3 for timeline.
A6: G-05 | B6: P0 | C6: Capacity Management & Zone Pricing | D6: Implement Pickeasy/Zapiet-level slot capacity engine: daily order limits per slot, per-location capacity configuration, dynamic zone-based rate calculation (by zipcode, distance, weight, cart value, product type), multi-location support (20+ locations with separate configs), preparation time buffers between slots. Pickeasy and Zapiet both Strong here — essential for Shopify merchants. | E6: S | F6: Pickeasy / Zapiet | G6: 4.5 | H6: RG | I6: PLANNED | J6: packages/core/src/slots/. API endpoints: slot availability, rate calculator, capacity check.
A7: G-06 | B7: P1 | C7: SMS/WhatsApp Customer Notifications | D7: Build multi-channel notification engine: SMS via Twilio (delivery scheduled confirmation, out-for-delivery alert with tracking link + time window, delivered confirmation), WhatsApp via Meta Business API (rich media messages with map preview), email templates (branded HTML), push notifications (web + mobile). Routific pattern: 'Your delivery is scheduled between 3:00pm-5:00pm. Track here: [link]'. ScrollEngine leads on WhatsApp integration. | E7: M | F7: Routific / ScrollEngine | G7: 4.5 | H7: SP | I7: PLANNED | J7: packages/core/src/notifications-v2/. Template engine with variables. Webhook delivery status.
A8: G-07 | B8: P1 | C8: Delivery Status Timeline UI | D8: Visual delivery status timeline component: Planned (timestamp) → Out for Delivery (timestamp + driver name) → Delivered (timestamp + POD photo thumbnail). Used in customer portal, tracking page, and admin dashboard. Routific's implementation is the gold standard — clean vertical timeline with icons, timestamps, and photo attachment at final step. | E8: S | F8: Routific | G8: 4.5 | H8: VS, PK | I8: PLANNED | J8: Shared component in packages/checkout-widget/. Reused across portal, tracking page, dashboard.
A9: G-08 | B9: P1 | C9: WooCommerce Deep Integration | D9: Build WooCommerce REST API adapter: order sync (bidirectional), checkout widget embedding via WooCommerce blocks, shipping method integration, webhook handlers for order status changes, product sync for delivery rules. Route4Me has WooCommerce support — we need deeper integration to serve non-Shopify merchants. Currently our WooCommerce support is only 'Adequate'. | E9: M | F9: Route4Me | G9: 4.6 | H9: AM | I9: PLANNED | J9: packages/core/src/integrations/woocommerce/. REST API v3 adapter. Block-based widget.
A10: G-09 | B10: P1 | C10: Google Maps & Calendar Integration | D10: Native Google Maps integration for zone visualization (draw delivery zones on map, calculate distances), address autocomplete in checkout widget, driver route display on map. Google Calendar sync for merchant order reminders (auto-create calendar events for pickup orders). Pickeasy has both — merchants love the Calendar reminder feature. | E10: S | F10: Pickeasy | G10: 4.6 | H10: AM, NK | I10: PLANNED | J10: packages/core/src/integrations/google/. Maps JS API + Calendar API.
A11: G-10 | B11: P1 | C11: Planned-vs-Actual Reporting | D11: Route analytics dashboard: planned route vs actual GPS path overlay on map, on-time delivery percentage, average delivery time per zone, driver performance scorecard, CO2 emissions tracking per route (distance × vehicle type factor), weekly/monthly trend charts. Route4Me and Routific both have this — essential for fleet operations customers. | E11: M | F11: Route4Me / Routific | G11: 4.6 | H11: AR, ZR | I11: PLANNED | J11: apps/dashboard/src/app/(dashboard)/analytics/routes/. Chart.js + Mapbox.
A12: G-11 | B12: P2 | C12: Telematics Gateway (Samsara + Geotab) | D12: Build a telematics adapter layer supporting major providers: Samsara (real-time vehicle location, fuel level, engine diagnostics), Geotab (MyGeotab API for speed, idling, harsh braking), with plugin architecture for Verizon Connect, Motive, Azuga, Fleet Complete, NexTraq. Route4Me integrates all of these — it's the enterprise fleet differentiator. | E12: L | F12: Route4Me | G12: 4.7 | H12: AM, PK | I12: PLANNED | J12: packages/core/src/telematics/. Adapter pattern. Start with Samsara + Geotab SDKs.
... A16: G-15 | B16: P3 | C16: AI Demand Prediction & Smart Scheduling | D16: Build AI-powered demand prediction: forecast delivery volume by zone/day/hour using historical patterns, suggest optimal slot allocation, auto-adjust capacity limits based on predicted demand, driver availability forecasting. Nobody has this across all 6 competitors — it's a genuine first-mover opportunity that strengthens our AI positioning. | E16: L | F16: Nobody (first-mover) | G16: 5.0+ | H16: ZR | I16: PLANNED | J16: packages/core/src/ai-demand/. Time-series forecasting. Integration with slot engine.
A18: SUMMARY | B18: 15 competitive gaps: 5× P0 (Sprint 4.5), 5× P1 (Sprint 4.5-4.6), 4× P2 (Sprint 4.7-4.9), 1× P3 (Sprint 5.0+). Benchmarked against: Fleetbase, ScrollEngine, Zapiet, Route4Me, Routific, Pickeasy.

Sheet Data Models Gap
A1: Old Model (MongoDB) | B1: Collection | C1: New Model (Prisma) | D1: Status | E1: Key Fields Missing in New | F1: Priority | G1: Notes | H1: Done | I1: Assignee | J1: Squad | K1: Work Status
A2: shopifyOrder | B2: shopify_orders | C2: Order | D2: EXISTS | E2: lineItems detail, billingAddress, shippingAddress, financialStatus, fulfillmentStatus, tags (rich), cancelledAt, refunds, discountCodes, taxLines, shippingLines, noteAttributes, orderRisk, orderSource | F2: P0 | G2: Core model - needs many Shopify-specific fields | H2: ☑ | I2: PK - Priya | J2: Core Backend | K2: DONE
A3: shipment | B3: shipments | C3: Shipment | D3: EXISTS | E3: Entire model: tracking_number, carrier, shipping_method, status lifecycle, label_url, customs_info, insurance, return_tracking, package_dimensions, weight, estimated_delivery_date, actual_delivery_date, shipping_cost, recipient_details, documents[], activity_log[] | F3: P0 | G3: Critical gap - old system had full shipment lifecycle separate from orders | H3: ☑ | I3: PK - Priya | J3: Core Backend | K3: DONE
A4: shipmentItem | B4: shipment_items | C4: ShipmentProof | D4: EXISTS | E4: Entire model: shipment_ref, product_id, variant_id, quantity, weight, dimensions, customs_value, hs_code, origin_country | F4: P0 | G4: Sprint 2.7 - 36-shipment-items.prisma | H4: ☑ | I4: PK - Priya | J4: Core Backend | K4: IN PROGRESS
A5: user | B5: users | C5: User | D5: EXISTS | E5: phone, avatar, permissions[], timezone, language, lastActiveAt, inviteToken, inviteExpiry, twoFactorEnabled, notificationPreferences | F5: P1 | G5: Old had richer user profiles | H5: ☑ | I5: AR - Arjun | J5: Architecture | K5: DONE
A6: userRole | B6: user_roles | C6: User.role (enum) | D6: EXISTS | E6: Full RBAC model with permissions array, resource-level access, customizable roles | F6: P1 | G6: Old had dynamic roles; new uses fixed enum | H6: ☑ | I6: AR - Arjun | J6: Architecture | K6: DONE
A7: userPermission | B7: user_permissions | C7: — | D7: MISSING | E7: Entire model: role_ref, resource, action, allow/deny, conditions | F7: P1 | G7: Granular permission system missing | H7: ☑ | I7: AR - Arjun | J7: Architecture | K7: DONE
A8: storeDetail | B8: store_details | C8: Shop | D8: EXISTS | E8: address, country, province, logo, favicon, social_links, business_hours, description, industry, defaultLanguage, supportEmail, returnPolicy, trackingPageConfig, widgetConfig, analyticsConfig | F8: P1 | G8: Shop model is minimal vs old storeDetail | H8: ☑ | I8: AR - Arjun | J8: Architecture | K8: DONE
A9: storeSettings | B9: store_settings | C9: Shop.settings (JSON) | D9: EXISTS | E9: Structured settings: autoAssign, proofOfDelivery, signatureRequired, realTimeTracking, driverAppConfig, customerNotificationDefaults, inventorySync, fulfillmentRules | F9: P1 | G9: Old had explicit fields; new uses opaque JSON | H9: ☑ | I9: AR - Arjun | J9: Architecture | K9: DONE
A10: storeApiSettings | B10: store_api_settings | C10: Integration | D10: EXISTS | E10: Old had dedicated model for API keys per provider (Google, Mapbox, Twilio, SendGrid, etc.) | F10: P2 | G10: Subsumed by Integration model but less explicit | H10: ☑ | I10: SP - Sanya | J10: Integrations | K10: DONE
A11: storeInfo | B11: store_infos | C11: Shop | D11: EXISTS | E11: Merged into Shop model | F11: — | G11: Consolidated correctly | H11: ☑ | I11: — | J11: — | K11: DONE
A12: calenderRule / calenderProfile | B12: calender_rules / calender_profiles | C12: — | D12: MISSING | E12: Entire models: blackout_dates[], operating_hours{}, preparation_time, cutoff_rules, holiday_calendars, recurring_rules, capacity_by_day, special_event_overrides | F12: P0 | G12: Sprint 2.5: calendar-engine.ts in shipping-profiles module | H12: ☑ | I12: VS - Vikram | J12: Core Backend | K12: DONE
... A40: billingSubscription | B40: billing_subscriptions | C40: Shop.planTier + billing routes | D40: EXISTS | E40: Entire model: shop_ref, plan_ref, status, current_period_start, current_period_end, cancelled_at, shopify_charge_id | F40: P1 | G40: Sprint 2.7 | H40: ☑ | I40: RG - Rohan | J40: Integrations | K40: IN PROGRESS
A42: SPRINT 2.8 PLANNED
A43: authProvider | B43: auth_providers | C43: AuthProvider | D43: PLANNED | E43: provider, type (auth0/clerk/cognito/firebase), config, enabled, tenant_scope | F43: P1 | G43: Sprint 2.8 - Auth provider registry | H43: ☐
A44: authSession | B44: auth_sessions | C44: AuthSession | D44: PLANNED | E44: userId, provider, externalId, accessToken, refreshToken, expiresAt, metadata | F44: P1 | G44: Sprint 2.8 - External auth sessions | H44: ☐
A45: platformAdmin | B45: platform_admins | C45: PlatformAdmin | D45: PLANNED | E45: email, role (super/admin/support), permissions, lastLogin, mfaEnabled | F45: P1 | G45: Sprint 2.8 - Platform admin panel | H45: ☐
A46: posConfig | B46: pos_configs | C46: POSConfig | D46: PLANNED | E46: shopId, formSchema, checkoutRules, shippingProfileRef | F46: P2 | G46: Sprint 2.8 - POS integration | H46: ☐

Sheet Feature Gap - Pages
A1: Feature Area | B1: Old Frontend Page(s) | C1: New Dashboard Page | D1: Status | E1: Missing Capabilities | F1: Priority | G1: Done | H1: Assignee | I1: Squad | J1: Work Status
A2: Dashboard / Home | B2: home/index.js + fullAnalytics | C2: / | D2: EXISTS | E2: Real-time sync status, data syncing banner, video tutorials, Polaris Viz charts, feature timeline | F2: P1 | G2: ☑ | H2: NK - Neha | I2: Frontend | J2: DONE
A3: Orders List | B3: orders/index.js | C3: /orders + /orders/create + /orders/[id] + /orders/bulk + /orders/import | D3: EXISTS | E3: Map view (Leaflet), CSV import modal, bulk actions, advanced filter presets, saved views | F3: P0 | G3: ☑ | H3: DM - Dev | I3: Frontend | J3: DONE
A4: Order Creation | B4: create-order/index.js | C4: /orders/create | D4: EXISTS | E4: Manual order creation form: customer details, line items, address, time slot, payment method, notes | F4: P0 | G4: ☑ | H4: DM - Dev | I4: Frontend | J4: DONE
A5: Order Details | B5: order-details/[...slug].js | C5: /orders/[id] | D5: EXISTS | E5: Full page view, shipment-in-order view, price breakdown, order tags editor, fulfillment actions, refund actions | F5: P0 | G5: ☑ | H5: DM - Dev | I5: Frontend | J5: DONE
A6: Shipments List | B6: shipments/index.js + local-delivery/shipments + store-pickup/shipments + standard-delivery/shipments | C6: /shipments | D6: EXISTS | E6: Entire shipment management: list, filters, map view, status tracking, bulk operations, multi-delivery-method views | F6: P0 | G6: ☑ | H6: DM - Dev | I6: Frontend | J6: DONE
A7: Shipment Details | B7: shipment-details/index.js + variants | C7: — | D7: EXISTS | E7: Full shipment detail: items, price breakdown, documents/POD, tracking notes, SMS confirmation, payment transactions, more actions | Sprint 2.4 - Shipment detail page | F7: P0 | G7: ☑ | H7: DM - Dev | I7: Frontend | J7: DONE
A8: Local Delivery Orders | B8: local-delivery/orders/index.js | C8: /orders/local | D8: EXISTS | E8: Delivery-method-specific order views with method-specific filters and actions | F8: P1 | G8: ☑ | H8: DM - Dev | I8: Frontend | J8: DONE
A9: Store Pickup | B9: store-pickup/* (4 pages) | C9: — | D9: EXISTS | E9: Store pickup workflow: orders, shipments, details, ready-for-pickup actions | Sprint 2.4 - Multi-store management | F9: P1 | G9: ☑ | H9: DM - Dev | I9: Frontend | J9: DONE
A10: Standard Delivery | B10: standard-delivery/* (4 pages) | C10: — | D10: MISSING | E10: Standard shipping workflow: orders, shipments, details, carrier assignment | F10: P1 | G10: ☐ | H10: DM - Dev | I10: Frontend | J10: NOT STARTED
A11: Routes List | B11: local-delivery/routes/index.js + routes/index.js | C11: /routes + /routes/create + /routes/[id] + /routes/[id]/edit | D11: EXISTS | E11: Route table pagination, search, timeline view, shipping label printing (4x6), CSV export, route claiming | F11: P0 | G11: ☑ | H11: NK - Neha | I11: Frontend | J11: DONE
A12: Route Create | B12: routes/create/index.js | C12: /routes/create | D12: EXISTS | E12: Route creation wizard: select shipments, assign driver, set start/end location, drag-and-drop ordering, map preview | F12: P0 | G12: ☑ | H12: DM - Dev | I12: Frontend | J12: DONE
... A40: Notifications | B40: — (none) | C40: /notifications | D40: EXISTS | E40: Notification center | F40: P2 | G40: ☑ | H40: SP | I40: Integrations | J40: DONE
A42: SPRINT 2.8 PLANNED
A43: Activity Log (Redesign) | B43: activity log viewer | C43: /activity | D43: PLANNED | E43: Full audit trail with filters, timeline, entity links, export — frontend-design skill | F43: P1 | G43: ☐ | H43: DM - Dev
A44: Settings Hub (Redesign) | B44: settings/* (8+ tabs) | C44: /settings/* | D44: PLANNED | E44: Unified settings with auth providers, branding, API keys, team — frontend-design skill | F44: P1 | G44: ☐ | H44: NK - Neha
A45: Platform Admin Panel | B45: — (new) | C45: /admin/* | D45: PLANNED | E45: User management, customer management, store oversight, metrics, platform config | F45: P1 | G45: ☐ | H45: DM - Dev
A46: Standard Delivery | B46: standard-delivery/* | C46: /delivery/standard | D46: PLANNED | E46: Standard shipping workflow: orders, shipments, carrier assignment | F46: P1 | G46: ☐ | H46: NK - Neha
A47: Auth Provider Config | B47: — (new) | C47: /settings/auth-providers | D47: PLANNED | E47: Auth0/Clerk/Cognito/Firebase provider setup, test connection, SAML/OIDC config | F47: P1 | G47: ☐ | H47: NK - Neha
A49: DESIGN SYSTEM (Sprint 3.0)
A50: shadcn/ui Component Preview | B50: Interactive component gallery with dark theme | C50: Sprint 3.0 | D50: Planned
A51: Design Tokens Page | B51: Visual token reference (colors, spacing, typography) | C51: Sprint 3.0 | D51: Planned
A52: Webhook Management | B52: Register, test, and monitor webhook endpoints | C52: Sprint 3.0 | D52: Planned
A53: Event Log Viewer | B53: Browse and filter platform event stream | C53: Sprint 3.0 | D53: Planned

Sheet Service & API Gap
A1: Service Domain | B1: Old Services (lmd-oms-v3) | C1: New API Routes (Fastify) | D1: Status | E1: Key Endpoints Missing | F1: Priority | G1: Done | H1: Assignee | I1: Squad | J1: Work Status
A2: Authentication | B2: users/userService (JWT + cookie sessions) | C2: routes/auth.ts | D2: EXISTS | E2: Google OAuth, password reset flow, email verification, 2FA, refresh token rotation, session management | F2: P0 | G2: ☑ | H2: AR - Arjun | I2: Architecture | J2: DONE
A3: Order CRUD | B3: orders/orderService + orderCountService | C3: routes/orders.ts | D3: EXISTS | E3: Manual order creation, order import (CSV), bulk status update, order merge/split, refund initiation, fulfillment creation | F3: P0 | G3: ☑ | H3: PK - Priya | I3: Core Backend | J3: DONE
A4: Shipment Lifecycle | B4: shipment/* (18 service files) | C4: — | D4: EXISTS | E4: Entire shipment domain: create from order, status transitions, assign to route, label generation, tracking updates, documents, payment tracking, activity log | F4: Sprint 2.4 - FileStorage (local + S3) | G4: ☑ | H4: PK - Priya | I4: Core Backend | J4: DONE
A5: Route Optimization | B5: serviceBus/mapbox + locationService/mapboxService + googleMapService | C5: packages/core/src/route-optimizer/ (5 files) | D5: EXISTS | E5: Nearest-neighbor, 2-opt, Clarke-Wright algorithms; ETA calculation; distance matrix | F5: P0 | G5: ☑ | H5: VS - Vikram | I5: Core Backend | J5: DONE
A6: Route Management | B6: shipment/shipmentRoutes + shipmentRouteDirection | C6: routes/routes.ts | D6: EXISTS | E6: Route CRUD exists but missing: optimization integration, direction rendering, stop reordering, driver notification on assignment, route claiming, label printing | F6: P0 | G6: ☑ | H6: VS - Vikram | I6: Core Backend | J6: DONE
A7: Location/Warehouse Mgmt | B7: — (via storeDetail) | C7: routes/locations-v2.ts (13 endpoints) | D7: EXISTS | E7: Working hours, capacity, zone associations, nearest location (Haversine) | F7: P0 | G7: ☑ | H7: VS - Vikram | I7: Core Backend | J7: DONE
A8: Shipping Profiles | B8: profiles/shippingProfile + calenderProfile | C8: — | D8: EXISTS | E8: Rate calculation engine, calendar rules, delivery windows, processing times, conditional rules, zone-based pricing | F8: Sprint 2.4 - FileStorage (local + S3) | G8: ☑ | H8: VS - Vikram | I8: Core Backend | J8: DONE
A9: Delivery Rules Engine | B9: shipment/shipmentRules + calenderRules/* | C9: — | D9: EXISTS | E9: Distance-based, weight-based, zone-based, time-based, product-category rules; min order; same-day/next-day logic | F9: Sprint 2.4 - Delivery rules engine | G9: ☑ | H9: VS - Vikram | I9: Core Backend | J9: DONE
A10: Carrier Rate Calculation | B10: carrierService/* (6 files) | C10: routes/carriers.ts | D10: EXISTS | E10: Rate calculator engine, natural load balancing, Shopify carrier service callback, multi-carrier comparison | F10: Sprint 2.4 - FileStorage (local + S3) | G10: ☑ | H10: VS - Vikram | I10: Core Backend | J10: DONE
A11: Notification Dispatch | B11: notifications/* (9 files) | C11: — | D11: EXISTS | E11: Email (SendGrid/SMTP), SMS (Twilio), WhatsApp (Meta Cloud API), Push (Firebase), Slack — all channel dispatchers | F11: Sprint 2.4 - FileStorage (local + S3) | G11: ☑ | H11: SP - Sanya | I11: Integrations | J11: DONE
A12: Notification Templates | B12: campaign/emailTemplate + whatsappTemplate | C12: — | D12: EXISTS | E12: Template CRUD, Unlayer email editor, WhatsApp template sync, variable interpolation, multi-language | F12: Sprint 2.4 - Campaign manager + template engine | G12: ☑ | H12: SP - Sanya | I12: Integrations | J12: DONE
... A51: Health Checks | B51: — (none) | C51: routes/health.ts | D51: EXISTS | E51: — (liveness + readiness + deep) | F51: P1 | G51: ☑ | H51: RG | I51: Backend | J51: DONE
A53: SPRINT 2.8 PLANNED
A54: Auth Provider Registry | B54: — (new) | C54: packages/core/src/auth/ | D54: PLANNED | E54: Multi-provider auth (Auth0, Clerk, Cognito, Firebase Auth, SAML, OIDC) with same BYOK pattern as routing/notifications | F54: P1 | G54: ☐ | H54: AR - Arjun
A55: Platform Admin API | B55: — (new) | C55: routes/admin.ts | D55: PLANNED | E55: User CRUD, customer management, store oversight, platform metrics, config management | F55: P1 | G55: ☐ | H55: PK - Priya
A56: POS Integration | B56: pos/posCustomFormService | C56: routes/pos.ts + core/pos/ | D56: PLANNED | E56: POS checkout, custom form builder, POS-specific shipping profiles | F56: P2 | G56: ☐ | H56: RG - Rohan
A57: Docker Production Deploy | B57: — (new) | C57: infra/docker/ | D57: PLANNED | E57: Multi-stage Dockerfiles, docker-compose.prod.yml, health checks, env config | F57: P1 | G57: ☐ | H57: AM - Aisha
A58: API Hardening | B58: — (existing) | C58: routes/*.ts | D58: PLANNED | E58: Zod validation on all routes, error standardization, OpenAPI spec generation | F58: P1 | G58: ☐ | H58: PK - Priya
A59: E2E Test Framework | B59: — (new) | C59: tests/e2e/ | D59: PLANNED | E59: Integration test suites, load testing scripts (k6), CI pipeline | F59: P2 | G59: ☐ | H59: KS - Kavitha
A61: EVENT SYSTEM (Sprint 3.0)
A62: Event Bus | B62: Typed event emitter + Redis Streams pub/sub | C62: Sprint 3.0 | D62: Planned
A63: Webhook API | B63: Registration, delivery, signing, retry routes | C63: Sprint 3.0 | D63: Planned
A64: Workflow Integration | B64: Auto-trigger workflows from existing API endpoints | C64: Sprint 3.0 | D64: Planned
A65: Socket.io Workflow Events | B65: Real-time workflow progress over WebSocket | C65: Sprint 3.0 | D65: Planned
A66: Shopify Workflow Bridge | B66: Shopify order webhook → createDeliveryOrder trigger | C66: Sprint 3.0 | D66: Planned

Sheet Infrastructure Gap
A1: Component | B1: Old System | C1: New Platform | D1: Status | E1: Action Required | F1: Priority | G1: Done | H1: Assignee | I1: Squad | J1: Work Status
A2: Database | B2: MongoDB (Mongoose + speed-goose caching) | C2: PostgreSQL + Prisma 6 | D2: EXISTS | E2: Data migration scripts needed for existing customers | F2: P0 | G2: ☑ | H2: AM - Aisha | I2: Platform | J2: DONE
A3: Message Queue | B3: Azure Service Bus (9 queues) | C3: packages/core/src/queue/ (7 consumers + base class) | D3: EXISTS | E3: BullMQ consumers: order-webhook, product-webhook, driver-tracking, event-scheduler + DLQ | F3: P0 | G3: ☑ | H3: AM - Aisha | I3: Platform | J3: DONE
A4: Cache Layer | B4: Redis (sessions + pub/sub + ORM cache) | C4: packages/core/src/cache/ | D4: EXISTS | E4: Redis client exists but caching strategy not implemented; need: session store, query cache, rate limiting, pub/sub for real-time | F4: P1 | G4: ☑ | H4: AM - Aisha | I4: Platform | J4: DONE
A5: Real-time | B5: Firebase Realtime Database + WebSocket | C5: Socket.io realtime layer | D5: EXISTS | E5: Need real-time infrastructure: WebSocket/SSE server, driver location streaming, order status push to customers | F5: P0 | G5: ☑ | H5: AM - Aisha | I5: Platform | J5: DONE
A6: File Storage | B6: Local + cloud (implied) | C6: — | D6: EXISTS | E6: Sprint 2.4 - Local + S3 file storage | F6: P1 | G6: ☑ | H6: AM - Aisha | I6: Platform | J6: DONE
A7: Process Manager | B7: PM2 (12 processes) | C7: Single Fastify + BullMQ workers | D7: EXISTS | E7: Workers exist as stubs; need full implementations | F7: Sprint 2.7 - process-manager with 4 workers | G7: ☑ | H7: AM - Aisha | I7: Platform | J7: NOT STARTED
A8: Geospatial | B8: Google Maps + Mapbox APIs | C8: geo-fence.ts + address.ts | D8: EXISTS | E8: Re-enable PostGIS, implement geocoding service, distance matrix, route optimization API | F8: P0 | G8: ☑ | H8: AM - Aisha | I8: Platform | J8: DONE
A9: Email Provider | B9: SendGrid / SMTP (via notification service) | C9: email/providers + dispatch | D9: EXISTS | E9: Email sending integration, template rendering, delivery tracking | F9: P0 | G9: ☑ | H9: SP - Sanya | I9: Integrations | J9: DONE
A10: SMS Provider | B10: Twilio (via smsService) | C10: sms/providers + dispatch | D10: EXISTS | E10: SMS sending, delivery receipts, phone number validation | F10: P1 | G10: ☑ | H10: SP - Sanya | I10: Integrations | J10: DONE
A11: WhatsApp | B11: Meta Cloud API (via whatsApp services) | C11: — | D11: MISSING | E11: WhatsApp Business API: template management, message sending, webhook handling | F11: P1 | G11: ☑ | H11: SP - Sanya | I11: Integrations | J11: DONE
A12: Push Notifications | B12: Firebase Cloud Messaging | C12: push-handler.ts (FCM) | D12: PARTIAL | E12: FCM integration for driver app push notifications | F12: P1 | G12: ☑ | H12: SP - Sanya | I12: Integrations | J12: DONE
... A24: E2E Test Suites | B24: — (none) | C24: 7 test files (4,439 lines) | D24: EXISTS | E24: — (compliance, cache, API tests) | F24: P2 | G24: ☑ | H24: KS | I24: QA | J24: DONE
A26: SPRINT 2.8 PLANNED
A27: Auth Provider Abstraction | B27: — (new) | C27: packages/core/src/auth/ | D27: PLANNED | E27: Multi-provider auth registry: Auth0, Clerk, AWS Cognito, Firebase Auth, generic OIDC, SAML 2.0 — same pattern as routing BYOK | F27: P1 | G27: ☐ | H27: AR - Arjun
A28: Docker Production Stack | B28: Docker + Azure scripts | C28: infra/docker/ | D28: PLANNED | E28: Multi-stage Dockerfiles, compose.prod.yml, Traefik reverse proxy, health checks, secrets management | F28: P1 | G28: ☐ | H28: AM - Aisha
A29: OpenAPI Spec | B29: — (new) | C29: docs/openapi.yaml | D29: PLANNED | E29: Auto-generated OpenAPI 3.1 spec from Fastify schemas, Swagger UI at /docs | F29: P2 | G29: ☐ | H29: PK - Priya
A31: DESIGN SYSTEM INFRA (Sprint 3.0)
A32: Tailwind CSS 4 | B32: PostCSS + Tailwind setup with --wl-* token bridge | C32: Sprint 3.0 | D32: Planned
A33: shadcn/ui Registry | B33: Component registry with Witylogix dark theme preset | C33: Sprint 3.0 | D33: Planned
A34: Redis Streams | B34: Event bus persistence layer for reliable pub/sub | C34: Sprint 3.0 | D34: Planned

Sheet Priority Roadmap
A1: Phase | B1: Sprint | C1: Work Item | D1: Category | E1: Est. Effort | F1: Dependencies | G1: Deliverable | H1: Done | I1: Assignee | J1: Squad | K1: Work Status
A2: Phase 1: Foundation | B2: 1-2 | C2: Authentication system (JWT, login, register, password reset) | D2: Backend + Frontend | E2: 2 weeks | F2: — | G2: Auth middleware, login/register pages, session management | H2: ☑ | I2: AR - Arjun | J2: Architecture | K2: DONE
A3: Phase 1: Foundation | B3: 1-2 | C3: PostGIS re-enable + geocoding service | D3: Backend + Infra | E3: 1 week | F3: — | G3: Spatial queries, point-in-polygon, distance calc | H3: ☑ | I3: AM - Aisha | J3: Platform | K3: DONE
A4: Phase 1: Foundation | B4: 1-2 | C4: Shipment model + migration | D4: Backend | E4: 1 week | F4: — | G4: Prisma schema + API routes for shipments | H4: ☑ | I4: PK - Priya | J4: Core Backend | K4: DONE
A5: Phase 1: Foundation | B5: 2-3 | C5: Location/Warehouse model + CRUD | D5: Backend + Frontend | E5: 2 weeks | F5: PostGIS | G5: Location management pages + API | H5: ☑ | I5: VS - Vikram | J5: Core Backend | K5: DONE
A6: Phase 1: Foundation | B6: 2-3 | C6: Calendar rules + delivery rules engine | D6: Backend | E6: 2 weeks | F6: — | G6: Scheduling engine, blackout dates, time windows | H6: ☑ | I6: VS - Vikram | J6: Core Backend | K6: DONE
A7: Phase 1: Foundation | B7: 3-4 | C7: Shipping profile system | D7: Backend + Frontend | E7: 2 weeks | F7: Locations, Zones, Rules | G7: Rate calculation, profile management UI | H7: ☑ | I7: VS - Vikram | J7: Core Backend | K7: DONE
A8: Phase 2: Core Ops | B8: 5-6 | C8: Order CRUD (full lifecycle + manual creation) | D8: Backend + Frontend | E8: 2 weeks | F8: Auth | G8: Order create page, detail page, status management | H8: ☑ | I8: PK - Priya | J8: Core Backend | K8: DONE
A9: Phase 2: Core Ops | B9: 5-6 | C9: Shipment lifecycle (create, track, deliver) | D9: Backend + Frontend | E9: 3 weeks | F9: Shipment model, Orders | G9: Shipment pages, status transitions, POD | H9: ☑ | I9: PK - Priya | J9: Core Backend | K9: DONE
A10: Phase 2: Core Ops | B10: 6-7 | C10: Route optimization (Mapbox/Google integration) | D10: Backend | E10: 2 weeks | F10: PostGIS, Drivers | G10: Distance matrix, route optimization API | H10: ☑ | I10: VS - Vikram | J10: Core Backend | K10: DONE
A11: Phase 2: Core Ops | B11: 7-8 | C11: Route creation + editing UI | D11: Frontend | E11: 2 weeks | F11: Route optimization | G11: Route create/edit pages with map + drag/drop | H11: ☑ | I11: DM - Dev | J11: Frontend | K11: DONE
A12: Phase 2: Core Ops | B12: 7-8 | C12: Webhook processing (order, product, customer, inventory) | D12: Backend | E12: 2 weeks | F12: BullMQ | G12: Queue consumers for each Shopify webhook type | H12: ☑ | I12: PK - Priya | J12: Core Backend | K12: DONE
... A36: Phase 6: Polish | B36: 24-25 | C36: CI/CD, Docker, monitoring | D36: Infra | E36: 2 weeks | F36: — | G36: Docker builds, Sentry, Pino logging, deployment | H36: ☑ | I36: AM - Aisha | J36: Platform | K36: DONE
A38: SPRINT 2.8 PLANNED
A39: Phase 7: Production | B39: 2.8 | C39: Auth provider abstraction (Auth0, Clerk, Cognito, Firebase, OIDC, SAML) | D39: Backend + Infra | E39: 2 weeks | F39: Auth system | G39: Multi-provider auth registry with BYOK pattern | H39: ☐
A40: Phase 7: Production | B40: 2.8 | C40: Platform admin panel (user/customer management) | D40: Backend + Frontend | E40: 2 weeks | F40: Auth, RBAC | G40: Admin dashboard for platform-level oversight | H40: ☐
A41: Phase 7: Production | B41: 2.8 | C41: Activity log & Settings redesign (frontend-design) | D41: Frontend | E41: 1 week | F41: Audit, Settings | G41: Production-grade UI with frontend-design skill | H41: ☐
A42: Phase 7: Production | B42: 2.8 | C42: Docker production deployment | D42: Infra | E42: 1 week | F42: — | G42: Multi-stage Dockerfiles, compose.prod.yml, health checks | H42: ☐
A43: Phase 7: Production | B43: 2.8 | C43: POS integration | D43: Backend | E43: 2 weeks | F43: Products, Payments | G43: POS checkout, custom forms | H43: ☐
A44: Phase 7: Production | B44: 2.8 | C44: API hardening + OpenAPI spec | D44: Backend | E44: 1 week | F44: All routes | G44: Zod validation, error standardization, Swagger UI | H44: ☐
A45: Phase 7: Production | B45: 2.8 | C45: E2E tests + load testing | D45: QA | E45: 1 week | F45: All apps | G45: Integration suites, k6 load tests, CI pipeline | H45: ☐
A47: PHASE 3.0: EVENT SYSTEM & DESIGN SYSTEM
A48: Design System Migration | B48: Migrate dashboard from custom components to shadcn/ui + Tailwind CSS 4 | C48: Phase 3.0 | D48: Sprint 3.0-3.1 | E48: CRITICAL
A49: Component Library (shadcn/ui) | B49: Install and configure shadcn/ui with Witylogix theme tokens | C49: Phase 3.0 | D49: Sprint 3.0 | E49: HIGH
A50: Tailwind CSS 4 Setup | B50: Add Tailwind CSS 4 to dashboard with --wl-* token mapping | C50: Phase 3.0 | D50: Sprint 3.0 | E50: HIGH
A51: Event Bus Foundation | B51: Typed event emitter with Redis Streams pub/sub | C51: Phase 3.0 | D51: Sprint 3.0 | E51: HIGH
A52: Workflow-API Integration | B52: Wire workflow engine into existing order/driver/delivery endpoints | C52: Phase 3.0 | D52: Sprint 3.0 | E52: HIGH
A53: Webhook System | B53: Outbound webhooks for workflow events with signing and retry | C53: Phase 3.0 | D53: Sprint 3.0 | E53: MEDIUM
A54: Real-time Workflow Updates | B54: Socket.io integration for live workflow step progression | C54: Phase 3.0 | D54: Sprint 3.0 | E54: MEDIUM
A55: Shopify Workflow Triggers | B55: Connect Shopify order webhooks to workflow engine | C55: Phase 3.0 | D55: Sprint 3.0 | E55: MEDIUM
A58: SPRINT 3.1 PLANNED
A60: SPRINT 3.2 PLANNED — Notification Providers, Carrier APIs, POS Extension & Page Migration (Date: 2026-03-08)
A61: Phase 3.2: Notifications & Carriers | B61: 3.2 | C61: ADR-012 notification architecture + orchestrator wiring | D61: Backend | E61: — | F61: — | G61: 3 files | H61: ☐ | I61: AR - Arjun | J61: Architecture | K61: PLANNED
A62: Phase 3.2: Notifications & Carriers | B62: 3.2 | C62: Page Tailwind migration batch 4 — orders/*, routes/* | D62: Frontend | E62: — | F62: — | G62: 10 pages | H62: ☐ | I62: DM - Dev | J62: Frontend | K62: PLANNED
A63: Phase 3.2: Notifications & Carriers | B63: 3.2 | C63: Page Tailwind migration batch 5 — delivery/*, shipping-profiles/*, collections, integrations | D63: Frontend | E63: — | F63: — | G63: 8 pages | H63: ☐ | I63: NK - Neha | J63: Frontend | K63: PLANNED
A64: Phase 3.2: Notifications & Carriers | B64: 3.2 | C64: SendGrid + Twilio real HTTP implementations | D64: Backend | E64: — | F64: — | G64: 2 files | H64: ☐ | I64: RG - Rohan | J64: Integrations | K64: PLANNED
A65: Phase 3.2: Notifications & Carriers | B65: 3.2 | C65: WhatsApp + Firebase Push real HTTP implementations | D65: Backend | E65: — | F65: — | G65: 2 files | H65: ☐ | I65: SP - Sanya | J65: Integrations | K65: PLANNED
A66: Phase 3.2: Notifications & Carriers | B66: 3.2 | C66: Page Tailwind migration batch 6 — analytics, billing, support, profile, notifications, stores | D66: Frontend | E66: — | F66: — | G66: 6 pages | H66: ☐ | I66: VS - Vikram | J66: Core Backend | K66: PLANNED
A67: Phase 3.2: Notifications & Carriers | B67: 3.2 | C67: FedEx + UPS carrier adapter real HTTP APIs | D67: Backend | E67: — | F67: — | G67: 2 files | H67: ☐ | I67: PK - Priya | J67: Core Backend | K67: PLANNED
A68: Phase 3.2: Notifications & Carriers | B68: 3.2 | C68: Notification provider tests + carrier adapter tests + validator tests | D68: QA | E68: — | F68: — | G68: 6 test suites | H68: ☐ | I68: KS - Kavitha | J68: QA | K68: PLANNED
A69: Phase 3.2: Notifications & Carriers | B69: 3.2 | C69: POS UI extension scaffold + checkout/POS shared components | D69: Backend + Frontend | E69: — | F69: — | G69: 8 files | H69: ☐ | I69: AM - Aisha | J69: Platform | K69: PLANNED
A71: SPRINT 3.3 PLANNED — Worker Wiring, Auth OAuth2, OSRM Routing & Final Page Migration (Date: 2026-03-08)
A72: Phase 3.3: Worker & Auth | B72: 3.3 | C72: ADR-013 worker-orchestrator architecture + notification worker rewrite to use orchestrator | D72: Backend | E72: — | F72: —
A73: Phase 3.3: Worker & Auth | B73: 3.3 | C73: Page Tailwind migration batch 7 — map, tracking/live, onboarding, widget-config, time-slots | D73: Frontend | E73: — | F73: —
A74: Phase 3.3: Worker & Auth | B74: 3.3 | C74: Page Tailwind migration batch 8 — auth/login, auth/register, auth/forgot-password, auth/layout, campaigns, campaigns/[id] | D74: Frontend | E74: — | F74: —
A75: Phase 3.3: Worker & Auth | B75: 3.3 | C75: DHL carrier adapter real HTTP + OSRM Phase 2 routing provider | D75: Backend | E75: — | F75: —
A76: Phase 3.3: Worker & Auth | B76: 3.3 | C76: Auth OAuth2 code exchange + API route BullMQ job wiring | D76: Backend + Frontend | E76: — | F76: —
A77: Phase 3.3: Worker & Auth | B77: 3.3 | C77: Page Tailwind migration batch 9 — page.tsx (home), widgets, routes/[id]/assign, admin/design-system, onboarding/layout, layout.tsx | D77: Frontend | E77: — | F77: —
A78: Phase 3.3: Worker & Auth | B78: 3.3 | C78: Notification worker integration tests + API route notification enqueueing | D78: Backend | E78: — | F78: —
A79: Phase 3.3: Worker & Auth | B79: 3.3 | C79: Validator schema tests + carrier adapter DHL tests + OSRM routing tests | D79: QA | E79: — | F79: —
A80: Phase 3.3: Worker & Auth | B80: 3.3 | C80: Shopify app webhook integration + checkout extension improvements | D80: Backend + Frontend | E80: — | F80: —
A82: SPRINT 3.4 PLANNED — Platform Abstraction, Competitive Intel & Final Tailwind Migration (Date: 2026-03-08)
A83: Phase 3.4: Platform Abstraction | B83: 3.4 | C83: Fleetbase competitive analysis + ADR-014 platform abstraction | D83: Backend | E83: — | F83: — | G83: 3 files | H83: ☐ | I83: AR - Arjun | J83: Architecture | K83: PLANNED
A84: Phase 3.4: Platform Abstraction | B84: 3.4 | C84: Page Tailwind migration batch 10 — stores, tracking-config, admin/shops/[id], profile, activity | D84: Frontend | E84: — | F84: — | G84: 5 pages, ~450 style conversions | H84: ☐ | I84: DM - Dev | J84: Frontend | K84: PLANNED
A85: Phase 3.4: Platform Abstraction | B85: 3.4 | C85: Page Tailwind migration batch 11 — drivers, calendar, notifications, admin/customers, shipments | D85: Frontend | E85: — | F85: — | G85: 5 pages, ~315 styles | H85: ☐ | I85: NK - Neha | J85: Frontend | K85: PLANNED
A86: Phase 3.4: Platform Abstraction | B86: 3.4 | C86: Platform source abstraction — Prisma schema + queue types + consumer refactor | D86: Backend | E86: — | F86: — | G86: 6 files | H86: ☐ | I86: RG - Rohan | J86: Core Backend | K86: PLANNED
A87: Phase 3.4: Platform Abstraction | B87: 3.4 | C87: Workflow platform abstraction + API route TODO stubs | D87: Backend + Frontend | E87: — | F87: — | G87: 5 files | H87: ☐ | I87: SP - Sanya | J87: Integrations | K87: PLANNED
A88: Phase 3.4: Platform Abstraction | B88: 3.4 | C88: Page Tailwind migration batch 12 — admin/workflows/[id], widget-config, shipping-profiles, admin/workflows, locations, admin/users | D88: Frontend | E88: — | F88: — | G88: 6 pages, ~176 styles | H88: ☐ | I88: VS - Vikram | J88: Frontend | K88: PLANNED
A89: Phase 3.4: Platform Abstraction | B89: 3.4 | C89: Analytics events DI injection + billing Shopify subscription status | D89: Backend | E89: — | F89: — | G89: 4 files | H89: ☐ | I89: PK - Priya | J89: Core Backend | K89: PLANNED
A90: Phase 3.4: Platform Abstraction | B90: 3.4 | C90: Platform abstraction tests + regression tests for refactored consumers | D90: QA | E90: — | F90: — | G90: 4 test suites | H90: ☐ | I90: KS - Kavitha | J90: QA | K90: PLANNED
A91: Phase 3.4: Platform Abstraction | B91: 3.4 | C91: Collections platform abstraction + collections Shopify GraphQL adapter | D91: Backend + Frontend | E91: — | F91: — | G91: 4 files | H91: ☐ | I91: AM - Aisha | J91: Platform | K91: PLANNED
A93: Phase 3: Competitive Parity
A94: Phase 3: Competitive Parity | B94: 4.5 | C94: Route Timeline Dispatcher Dashboard | D94: Frontend + Backend | E94: 2 weeks | F94: Event Bus, Route Optimization | G94: Routific-quality dispatch view with color-coded routes + timeline | H94: ☐ | I94: AR - Arjun | J94: Architecture | K94: PLANNED
A95: Phase 3: Competitive Parity | B95: 4.5 | C95: Checkout Date/Time Picker Widget | D95: Frontend + Package | E95: 2 weeks | F95: Slot Engine API | G95: Pickeasy-quality embeddable widget with slots, blackout, zip validation | H95: ☐ | I95: NK - Nikhil | J95: Frontend | K95: PLANNED
A96: Phase 3: Competitive Parity | B96: 4.5 | C96: Customer Self-Service Portal | D96: Frontend (New App) | E96: 2 weeks | F96: Auth, Orders API | G96: Next.js portal: order history, tracking, reschedule, preferences | H96: ☐ | I96: DM - Deepak | J96: Frontend | K96: PLANNED
A97: Phase 3: Competitive Parity | B97: 4.5 | C97: Slot Engine API & Capacity Management | D97: Backend | E97: 1.5 weeks | F97: Prisma models | G97: Slot availability, capacity limits, zone-rate calculator, deadlines | H97: ☐ | I97: RG - Rahul | J97: Core Backend | K97: PLANNED
A98: Phase 3: Competitive Parity | B98: 4.5 | C98: POD v2: Photo + Signature + QR | D98: Backend + Mobile | E98: 2 weeks | F98: S3/R2 storage | G98: Multi-method POD with delivery status timeline + cloud storage | H98: ☐ | I98: PK - Priya | J98: Core Backend | K98: PLANNED
A99: Phase 3: Competitive Parity | B99: 4.5 | C99: Customer Notification Engine v2 | D99: Backend + Integration | E99: 2 weeks | F99: Twilio, Meta Business | G99: Email + SMS + WhatsApp + push with template engine | H99: ☐ | I99: SP - Sanjay | J99: Full-stack | K99: PLANNED
A100: Phase 3: Competitive Parity | B100: 4.5 | C100: Checkout & Dispatch Component Library | D100: Frontend | E100: 1.5 weeks | F100: Design system | G100: DatePicker, TimeSlotGrid, RouteTimeline, DriverCard, StopMarker | H100: ☐ | I100: VS - Vikram | J100: Frontend | K100: PLANNED
A101: Phase 3: Competitive Parity | B101: 4.5 | C101: E2E: Dispatch, Checkout & Portal | D101: QA | E101: 2 weeks | F101: All Sprint 4.5 features | G101: Playwright suites for dispatch, checkout, portal, POD, notifications | H101: ☐ | I101: KS - Kavitha | J101: QA | K101: PLANNED
A102: Phase 3: Competitive Parity | B102: 4.5 | C102: Shopify Checkout Extension + Google Maps | D102: Integration | E102: 2 weeks | F102: Checkout widget | G102: Shopify extension, Google Maps zone viz, Calendar sync | H102: ☐ | I102: AM - Aisha | J102: Platform | K102: PLANNED
A103: Phase 3: Competitive Parity | B103: 4.5 | C103: Smart Slot Recommendation + ML ETA | D103: AI/ML | E103: 2 weeks | F103: Slot Engine, historical data | G103: ML slot recommender + traffic-aware ETA (3-5 models) | H103: ☐ | I103: ZR - Zara | J103: AI | K103: PLANNED
A104: Phase 3: Competitive Parity | B104: 4.6 | C104: WooCommerce Deep Integration | D104: Integration | E104: 2 weeks | F104: Checkout widget, Orders API | G104: WooCommerce REST API adapter, checkout block, webhook sync | H104: ☐ | I104: AM - Aisha | J104: Platform | K104: PLANNED
A105: Phase 3: Competitive Parity | B105: 4.6 | C105: Google Maps & Calendar Native Integration | D105: Integration | E105: 1 week | F105: Maps JS API | G105: Zone visualization, address autocomplete, Calendar order reminders | H105: ☐ | I105: NK - Nikhil | J105: Frontend | K105: PLANNED
... A111: Phase 4: Market Leadership | B111: 5.0 | C111: AI Demand Prediction & Smart Scheduling | D111: AI/ML | E111: 4 weeks | F111: Historical delivery data | G111: Time-series demand forecasting, auto capacity adjustment | H111: ☐ | I111: ZR - Zara | J111: AI | K111: PLANNED

Sheet Statistics
A1: Gap Statistics Summary | AA1: Sprint 4.5 | AB1: Sprint 4.6 | AC1: Sprint 4.7
AD2: Sprint 4.8
A3: SPRINT PROGRESS (as of Sprint 4.5) | B3: SPRINT PROGRESS (as of Sprint 4.7) | AA3: Customer Experience & Checkout | AD3: 2600
A4: Last Updated: Sprint 4.5 (2026-03-11) | B4: Last Updated: Sprint 4.7 (2026-03-11) | AA4: 1 (customer-portal) | AD4: 883700
A5: Metric | B5: Sprint 1.1 | C5: Sprint 1.2 | D5: Sprint 2.0 | E5: Sprint 2.1 | F5: Sprint 2.3 | G5: Sprint 2.4 | H5: Sprint 2.5 | I5: Sprint 2.6 | J5: Sprint 2.7 | K5: Sprint 2.8 | L5: Sprint 2.9 | M5: Sprint 3.0 | N5: Sprint 3.1 | O5: Sprint 3.3 | P5: Sprint 3.4 | Q5: Sprint 3.5 | R5: Sprint 3.6 | S5: Sprint 3.7 | T5: Sprint 3.8 | U5: Sprint 3.9 | V5: Sprint 4.0 | W5: Sprint 4.1 | X5: Sprint 4.2 | Y5: Sprint 4.3 | Z5: Sprint 4.4 | AA5: Sprint 4.5 | AB5: 3280 | AC5: 2467 | AD5: 94
A6: Source Files | B6: 184 | C6: 258 | D6: 325 | E6: 418 | F6: 429 | G6: 461 | H6: 512 | I6: 555 | J6: 794 | K6: 848 | L6: 1565 | M6: 1609 | N6: 1700 | O6: 1800 | P6: 1860 | Q6: 1900 | R6: 1960 | S6: 2000 | T6: 2050 | U6: 2100 | V6: 2200 | W6: 2280 | X6: 2320 | Y6: 2343 | Z6: 2410 | AA6: 2593 | AB6: 803280 | AC6: 845846 | AD6: 146
A7: Lines of Code | B7: 22541 | C7: 40672 | D7: 58339 | E7: 83232 | F7: 113346 | G7: 130966 | H7: 153011 | I7: 168753 | J7: 208287 | K7: 221000 | L7: 156361 | M7: 170399 | N7: 200000 | O7: 225000 | P7: 235000 | Q7: 248000 | R7: 262000 | S7: 280000 | T7: 298000 | U7: 320000 | V7: 350000 | W7: 371000 | X7: 383000 | Y7: 392000 | Z7: 423000 | AA7: 468604 | AB7: 80 | AC7: 88 | AD7: 483
A8: Dashboard Pages | B8: 10 | C8: 14 | D8: 18 | E8: 24 | F8: 37 | G8: 47 | H8: 50 | I8: 50 | J8: 57 | K8: 64 | L8: 65 | M8: 66 | N8: 66 | O8: 66 | P8: 66 | Q8: 66 | R8: 66 | S8: 66 | T8: 66 | U8: 66 | V8: 66 | W8: 66 | X8: 70 | Y8: 70 | Z8: 74 | AA8: 76 | AB8: 133 | AC8: 138 | AD8: 41
A9: API Routes | B9: 8 | C9: 12 | D9: 18 | E9: 25 | F9: 27 | G9: 39 | H9: 42 | I9: 44 | J9: 51 | K9: 55 | L9: 63 | M9: 67 | N9: 75 | O9: 75 | P9: 70 | Q9: 71 | R9: 73 | S9: 73 | T9: 73 | U9: 73 | V9: 73 | W9: 73 | X9: 74 | Y9: 74 | Z9: 75 | AA9: 83 | AB9: 107 | AC9: 39
A10: Prisma Models | B10: 18 | C10: 22 | D10: 26 | E10: 30 | F10: 32 | G10: 34 | H10: 26 | I10: 25 | J10: 28 | K10: 30 | L10: 30 | M10: 31 | N10: 31 | O10: 31 | P10: 31 | Q10: 31 | R10: 31 | S10: 31 | T10: 31 | U10: 31 | V10: 31 | W10: 31 | X10: 31 | Y10: 31 | Z10: 35 | AA10: 37 | AB10: 65 | AC10: 70
A11: Core Modules | B11: 4 | C11: 6 | D11: 8 | E11: 12 | F11: 18 | G11: 32 | H11: 38 | I11: 43 | J11: 48 | K11: 51 | L11: 51 | M11: 57 | N11: 62 | O11: 66 | P11: 68 | Q11: 72 | R11: 74 | S11: 74 | T11: 74 | U11: 74 | V11: 74 | W11: 74 | X11: 74 | Y11: 74 | Z11: 80 | AA11: 90 | AB11: 247 | AC11: 266
A12: Test Files | B12: 0 | C12: 0 | D12: 0 | E12: 0 | F12: 22 | G12: 29 | H12: 37 | I12: 44 | J12: 51 | K12: 57 | L12: 63 | M12: 69 | P12: 73 | Q12: 77 | R12: 85 | S12: 99 | T12: 114 | U12: 139 | V12: 180 | W12: 180 | X12: 190 | Y12: 191 | Z12: 205 | AA12: 127 | AB12: 280 | AC12: 310
A13: Shopify Pages | N13: 12 | O13: 12 | P13: 12 | Q13: 12 | R13: 12 | S13: 12 | T13: 12 | U13: 12 | V13: 12 | W13: 12 | X13: 12 | Y13: 12 | Z13: 12 | AA13: 12 | AB13: 2800 | AC13: 3300
A14: Test Suites | N14: 75 | O14: 85 | P14: 89 | Q14: 93 | R14: 101 | S14: 115 | T14: 130 | U14: 155 | V14: 180 | W14: 180 | X14: 190 | Y14: 191 | Z14: 205 | AA14: 210 | AB14: 73 | AC14: 73
A15: Test Cases | N15: 250 | O15: 280 | P15: 310 | Q15: 434 | R15: 844 | S15: 1763 | T15: 2534 | U15: 3808 | V15: 4676 | W15: 4676 | X15: 4817 | Y15: 4817 | Z15: 4900 | AA15: 2100 | AB15: 55 | AC15: 70
A16: Workers/Consumers | B16: Deliverable | C16: Files | D16: Lines | E16: Status | N16: 8 | O16: 8 | P16: 8 | Q16: 9 | R16: 12 | S16: 12 | T16: 12 | U16: 12 | V16: 12 | Y16: 12 | Z16: 12 | AB16: 3 | AC16: 3
A17: Real-time Channels | B17: Route optimization engine (3 algorithms + ETA) | C17: 7 | D17: 1610 | E17: DONE | N17: 4 | O17: 4 | P17: 4 | Q17: 4 | R17: 4 | S17: 4 | T17: 4 | U17: 4 | V17: 4 | Y17: 4 | Z17: 4 | AB17: 1 | AC17: 1
A18: Workflow Definitions | B18: Shipping profiles detail, route assign, local orders pages | C18: 3 | D18: 1572 | E18: DONE | N18: 10 | O18: 10 | P18: 10 | Q18: 10 | R18: 10 | S18: 10 | T18: 10 | U18: 10 | V18: 10 | Y18: 10 | Z18: 10 | AB18: 1 | AC18: 1
A19: Queue Types | B19: Cart plugin components (date picker, time slots, rates) | C19: 5 | D19: 1817 | E19: DONE | N19: 8 | O19: 8 | P19: 8 | Q19: 8 | R19: 8 | S19: 8 | T19: 8 | U19: 8 | V19: 8 | Y19: 8 | Z19: 8 | AB19: 1 | AC19: 1
A20: RG - Rohan | B20: Queue consumers (4 types) + spatial queries module | C20: 10 | D20: 3813 | E20: DONE | AB20: 1 | AC20: 1
A21: SP - Sanya | B21: Payment processing (gateway + processor + Prisma) | C21: 6 | D21: 2689 | E21: DONE | AB21: 1 | AC21: 1
A22: VS - Vikram | B22: Shipping profiles core (rate calc, calendar, validator) | C22: 6 | D22: 3068 | E22: DONE | AB22: 15 | AC22: 15
A23: PK - Priya | B23: Analytics engine (event tracker, aggregator, dashboard) | C23: 6 | D23: 2275 | E23: DONE | AB23: 1 | AC23: 1
A24: KS - Kavitha | B24: 8 test suites (optimizer, payments, analytics, queue, etc.) | C24: 8 | D24: 5184 | E24: DONE | AB24: 25 | AC24: 26
A25: AM - Aisha | B25: Migration framework + location management API | C25: 5 | D25: 1914 | E25: DONE | AB25: 14 | AC25: 14
AB26: 11 | AC26: 13
A27: SPRINT 2.6 DELIVERABLES
A36: PK - Priya | B36: Campaign, messaging, audit, permissions API routes | C36: 4 | D36: 2469 | E36: DONE
A37: KS - Kavitha | B37: 7 test suites (RBAC, audit, dispatcher, crypto, etc.) | C37: 7 | D37: 4725 | E37: DONE
A38: AM - Aisha | B38: Shopify campaigns, templates, audit log routes | C38: 5 | D38: 1628 | E38: DONE
A40: SPRINT 2.7 DELIVERABLES
A48: VS - Vikram | B48: Saved views engine + widget manager core modules | C48: 6 | D48: 1566 | E48: DONE
A49: PK - Priya | B49: 6 API routes (billing, support, features, views, widgets, collections) | C49: 7 | D49: 2708 | E49: DONE
A50: KS - Kavitha | B50: 7 test suites (subscription, quota, collections, support, views, widgets, process) | C50: 7 | D50: 3930 | E50: DONE
A51: AM - Aisha | B51: 5 Shopify routes (billing, invoices, support, support detail, collections) | C51: 5 | D51: 2233 | E51: DONE
A53: SPRINT 2.8 DELIVERABLES
E55: Remaining | F55: % Complete
E56: =B56-C56-D56 | F56: =C56/B56
E57: =B57-C57-D57 | F57: =C57/B57
E58: =B58-C58-D58 | F58: =C58/B58
E59: =B59-C59-D59 | F59: =C59/B59
E60: =B60-C60-D60 | F60: =C60/B60
A61: VS - Vikram | B61: Standard delivery workflow pages | C61: 2 | D61: 600
A62: PK - Priya | B62: Docker production stack (multi-stage, compose, nginx) | C62: 5 | D62: 800
A63: KS - Kavitha | B63: 6 test suites (auth, POS, errors, rate limit, validator, admin) | C63: 6 | D63: 1800
A64: AM - Aisha | B64: 3 Shopify routes (auth-providers, POS index, POS detail) | C64: 3 | D64: 900
A66: SPRINT 2.9 DELIVERABLES
A68: Agent | B68: Deliverable | C68: Files | D68: Lines
A69: AR - Arjun | B69: Workflow engine (DI container, step runner, compensation, registry, hooks) | C69: 10 | D69: 3100
A70: DM - Dev | B70: Workflow executions list page (StatCards, filters, search, table) | C70: 1 | D70: 462
A71: NK - Neha | B71: Workflow execution detail page (step timeline, JSON viewer, retry) | C71: 1 | D71: 701
A72: RG - Rohan | B72: 3 workflow definitions (createDeliveryOrder, assignDriver, completeDelivery) | C72: 6 | D72: 4300
A73: SP - Sanya | B73: 12 reusable workflow steps (validation, geocoding, rating, assignment, etc.) | C73: 9 | D73: 2439
A74: VS - Vikram | B74: BullMQ durable execution (queue, worker, scheduler, DLQ) | C74: 6 | D74: 1397
A75: PK - Priya | B75: 4 workflow API route files (orders, drivers, delivery, executions) | C75: 4 | D75: 1660
A76: KS - Kavitha | B76: 6 test suites (engine, container, step-runner, 3 workflow tests) | C76: 6 | D76: 3194
A77: AM - Aisha | B77: ADR-009 + Architecture debate (blue/red team standup) | C77: 2 | D77: 800
A79: COMPLETION SUMMARY
A80: Category | B80: Total Items | C80: 31 | D80: 72.1%
A81: Data Models | B81: 43 | C81: 66 | D81: 169.2%
A82: Feature Pages | B82: 39 | C82: 67 | D82: 167.5%
A83: API Services | B83: 40 | C83: 63 | D83: 157.5%
A84: Infrastructure | B84: 24 | C84: 38 | D84: 90.5%
A85: Roadmap Items | B85: 42 | C85: 35 | D85: 83.3%
A87: SPRINT 3.0 PLANNED
A89: Agent | B89: Deliverable | C89: Focus | D89: Category
A90: AR - Arjun | B90: Event bus + ADR-010 event architecture | C90: Backend | D90: Architecture
A91: DM - Dev | B91: shadcn/ui migration Phase 1 (Button, Card, Badge, Input, Select, Modal) | C91: Frontend | D91: Design System
A92: NK - Neha | B92: shadcn/ui migration Phase 2 (Table, Tabs, Toast, StatCard, EmptyState) | C92: Frontend | D92: Design System
A93: RG - Rohan | B93: Workflow-API integration (wire workflows into existing endpoints) | C93: Backend | D93: Integration
A94: SP - Sanya | B94: Webhook system (registration, signing, retry, delivery tracking) | C94: Full-stack | D94: Events
A95: VS - Vikram | B95: Tailwind CSS 4 + design tokens bridge (--wl-* → Tailwind) | C95: Frontend | D95: Design System
A96: PK - Priya | B96: Socket.io workflow events + real-time step progression | C96: Backend | D96: Events
A97: KS - Kavitha | B97: Integration tests + component visual regression tests | C97: QA | D97: Testing
A98: AM - Aisha | B98: Shopify workflow triggers + webhook management UI | C98: Integration | D98: Shopify
A100: SPRINT 3.0 DELIVERABLES
A102: Agent | B102: Deliverable | C102: Files | D102: Lines | E102: Status
A103: AR - Arjun | B103: TypedEventBus (Redis Streams + InMemory), ADR-010 | C103: 7 | D103: 2873 | E103: DONE
A104: DM - Dev | B104: shadcn/ui Phase 1: button, card, badge, input, select, modal + Tailwind config | C104: 9 | D104: 546 | E104: DONE
A105: NK - Neha | B105: shadcn/ui Phase 2: table, tabs, toast, stat-card, empty-state + dropdown/skeleton/tooltip | C105: 8 | D105: 866 | E105: DONE
A106: RG - Rohan | B106: Workflow-API integration (auto-trigger, hooks, Fastify plugin) | C106: 4 | D106: 1348 | E106: DONE
A107: SP - Sanya | B107: Outbound webhook system (manager, delivery, processor, emitter, routes, Prisma) | C107: 8 | D107: 2186 | E107: DONE
A108: VS - Vikram | B108: Design system foundation (tokens, header/sidebar migration, barrel export, gallery) | C108: 5 | D108: 1255 | E108: DONE
A109: PK - Priya | B109: Socket.io realtime workflow events + SSE fallback + plugin | C109: 5 | D109: 1208 | E109: DONE
A110: KS - Kavitha | B110: 6 test suites (event-bus, webhook, workflow-integration, realtime, UI, routes) | C110: 6 | D110: 2183 | E110: DONE
A111: AM - Aisha | B111: Shopify webhook management (API handler, config, detail, event picker) | C111: 4 | D111: 1884 | E111: DONE
A113: SPRINT 3.1 PLANNED
A115: Agent | B115: Deliverable | C115: Focus | D115: Category
A116: AR - Arjun | B116: ADR-011, extension-core package | C116: 8 files | D116: Extensions
A117: DM - Dev | B117: Page migration batch 1 (Tailwind) | C117: 7 pages | D117: Design System
A118: NK - Neha | B118: Page migration batch 2 (Tailwind) | C118: 7 pages | D118: Design System
A119: VS - Vikram | B119: Page migration batch 3 (Tailwind) | C119: 6 pages | D119: Integration
A120: RG - Rohan | B120: Queue consumer DB integration | C120: 4 files | D120: Events
A121: SP - Sanya | B121: Event-webhook bridge | C121: 5 files | D121: Design System
A122: PK - Priya | B122: File storage + push notifications | C122: 8 files | D122: Infrastructure
A123: KS - Kavitha | B123: Integration tests | C123: 6 test suites | D123: Testing
A124: AM - Aisha | B124: Checkout UI extension | C124: 10 files | D124: Shopify
A125: TOTAL | B125: Sprint 3.1 Deliverables | C125: 58 files + 6 test suites | D125: 24,767 lines

Sheet Standup Notes & Actions
A1: WITYLOGIX — STANDUP NOTES & ACTION ITEMS
A2: Architecture Pivot Debate — 2026-03-07 | Sprint 2.9 Kickoff
A3: Sprint 4.0 Standup — 2026-03-10 — Documentation Engine Discussion
A4: Docs Engine | B4: Fumadocs (Next.js, open-source, MDX, AI-ready)
A5: Location
A6: AI Search | B6: Anthropic Claude API for RAG-powered doc chat
A7: API Reference | B7: Auto-generated from OpenAPI 3.0 spec | C7: Scope | D7: Key Deliverables | E7: Status
A8: TypeScript SDK | B8: packages/sdk auto-generated from OpenAPI | C8: Workflow Engine ONLY | D8: packages/framework/, 3 core workflows (createDeliveryOrder, assignDriver, completeDelivery), BullMQ backing | E8: Sprint 2.9 — In Progress
A9: Design | B9: Dark-first, --wl-* CSS vars, industrial aesthetic | C9: Event Bus | D9: Redis-backed event bus, notification/analytics/webhook subscribers, event-driven side effects | E9: Deferred
A10: Component Gallery | B10: 23 components with live previews | C10: Module Links + Plugin System | D10: defineLink cross-module relations, plugin API (modules+workflows+hooks+subscribers as npm packages) | E10: Deferred
A11: Target | B11: Sprint 4.1 — all 9 agents
A13: BLUE/RED TEAM CONSENSUS
A14: Agreement | B14: Blue Team Position | C14: Red Team Position | D14: Resolution
A15: BYOK Pattern | B15: Keep it | C15: Keep it | D15: Unanimous — BYOK stays
A16: Prisma ORM | B16: Keep it (no DML/MikroORM) | C16: Keep it | D16: Unanimous — Prisma stays
A17: Fastify Framework | B17: Keep it | C17: Keep it | D17: Unanimous — Fastify stays
A18: RLS Multi-tenancy | B18: Keep it | C18: Keep it | D18: Unanimous — RLS stays
A19: Workflow Engine | B19: Build NOW in Sprint 2.9 | C19: Defer until pain is proven | D19: Blue won — build NOW, prove on 3 workflows
A20: Event Bus | B20: Build in Phase 1 | C20: Defer until 10 customers | D20: Red won — defer to Phase 2
A21: Module Links | B21: Build in Phase 2 | C21: Defer until 50 customers | D21: Red won — defer to Phase 3
A22: Plugin System | B22: Build in Phase 2 | C22: Defer until customer demand | D22: Red won — defer to Phase 3
A23: 18-Month Roadmap | B23: Commit to full timeline | C23: Re-evaluate after each phase | D23: Red won — no timeline commitment
A26: SPRINT 2.9 ACTION ITEMS
A27: ID | B27: Owner | C27: Squad | D27: Action | E27: Deliverable | F27: Sprint | G27: Status
A28: 1 | B28: AR - Arjun | C28: Architecture | D28: Design packages/framework/ with workflow engine, container DI, step runner | E28: Workflow engine framework (10 files, 1,738 lines) | F28: 2.9 | G28: Done
A29: 2 | B29: RG - Rohan | C29: Core Backend | D29: Define interfaces for WorkflowStep, WorkflowContext, StepCompensation | E29: Workflow steps library (12 steps, 2,413 lines) | F29: 2.9 | G29: Done
A30: 3 | B30: PK - Priya | C30: Core Backend | D30: Implement createDeliveryOrderWorkflow as proof-of-concept | E30: 9-step workflow with 3-step compensation (1,496 lines) | F30: 2.9 | G30: Done
A31: 4 | B31: SP - Sanya | C31: Core Backend | D31: Implement assignDriverWorkflow using the framework | E31: 10-step workflow with scoring algorithm (1,239 lines) | F31: 2.9 | G31: Done
A32: 5 | B32: NK - Neha | C32: Core Backend | D32: Implement completeDeliveryWorkflow | E32: 11-step workflow with POD verification (1,576 lines) | F32: 2.9 | G32: Done
A33: 6 | B33: KS - Kavitha | C33: QA | D33: Write test suites for all 3 workflows (step + workflow level) | E33: 6 test files, 240+ test cases (3,194 lines) | F33: 2.9 | G33: Done
A34: 7 | B34: DM - Dev | C34: Frontend | D34: Dashboard page: workflow execution viewer | E34: List + detail pages with step timeline (1,163 lines) | F34: 2.9 | G34: Done
A35: 8 | B35: VS - Vikram | C35: Core Backend | D35: Refactor 3 existing API routes to call workflows | E35: 4 workflow route files (1,660 lines) | F35: 2.9 | G35: Done
A36: 9 | B36: AM - Aisha | C36: Platform | D36: BullMQ integration for durable workflow execution | E36: Queue, worker, scheduler, dead-letter (1,397 lines) | F36: 2.9 | G36: Done
A37: 10 | B37: ALL | C37: ALL | D37: After Sprint 2.9: review, retrospective, decide Phase 2 scope | E37: Retrospective document | F37: 3.0 | G37: Planned
A40: REFERENCE DOCUMENTS
A41: ADR-009: | B41: docs/adr/ADR-009-medusa-inspired-architecture-evolution.md
A42: Standup Notes: | B42: docs/sprint-notes/STANDUP-2026-03-07-architecture-debate.md
A43: Blue Team: | B43: AR (CTO), DM (Frontend), NK (Frontend Lead), KS (QA Lead)
A44: Red Team: | B44: RG (Backend Lead), SP (Full-stack), PK (Sr. Backend), VS (Component Dev), AM (Integration)
A46: Sprint 4.2 Standup — 2026-03-10
A47: Sprint 4.2 shipped: ADR-021, SDK tests (141 cases), seed script, driver app screens, settings page, webhook dashboard, 5 new UI components, smoke test, CI updates
A48: Deep dive: CLI deployment tool for one-line VM deployment
A49: Decision: Pure bash CLI (witylogix) with 12 subcommands — install, deploy, upgrade, status, logs, backup, restore, ssl, env, doctor, scale, destroy
A50: Decision: Caddy for reverse proxy with auto-SSL (api/app/docs subdomain routing)
A51: Decision: AI subcommands (ai setup, ai diagnose) for Claude-powered diagnostics
A52: NEW TEAM MEMBER: ZR — Zara (AI Engineer) — AI-powered features, docs search, CLI diagnostics, log analysis
A53: Sprint 4.3 planned: Full CLI tool (infra/cli/witylogix), Caddy templates, production Docker Compose, AI diagnostics, CLI tests

Sheet Sprint 3.5 Plan
A1: Sprint 3.5 — TODO Cleanup, Platform Abstraction Phase 2, WooCommerce Adapter & Final Tailwind Push
A3: Agent | B3: Deliverable | C3: Files (est) | D3: Lines (est) | E3: Status
A4: AR - Arjun | B4: ADR-015 WooCommerce integration + adapter architecture | C4: 3 | D4: 1200 | E4: PLANNED
A5: RG - Rohan | B5: Platform abstraction Phase 2 (workflow-integration, inventory, integrations) | C5: 6 | D5: 1800 | E5: PLANNED
A6: SP - Sanya | B6: TODO stub cleanup — API routes (routes.ts, collections.ts, integration-worker) | C6: 4 | D6: 800 | E6: PLANNED
A7: PK - Priya | B7: TODO stub cleanup — Core modules (campaigns, event-bus, notifications, orchestrator) | C7: 5 | D7: 600 | E7: PLANNED
A8: DM - Dev | B8: Tailwind migration batch 13: drivers (76 styles), onboarding (73 styles) | C8: 2 | D8: 1400 | E8: PLANNED
A9: NK - Nisha | B9: Tailwind migration batch 14: shipping-profiles, locations, admin, register | C9: 4 | D9: 1200 | E9: PLANNED
A10: VS - Vikram | B10: Tailwind migration batch 15: inventory, login, admin/customers, delivery, forgot-password | C10: 5 | D10: 1000 | E10: PLANNED
A11: KS - Kavitha | B11: Test suites: WooCommerce adapter, TODO-fix integration, workflow platform tests | C11: 4 | D11: 2800 | E11: PLANNED
A12: AM - Aisha | B12: WooCommerce webhook consumer + REST API adapter (orders/products/inventory) | C12: 5 | D12: 2000 | E12: PLANNED
A13: TOTALS | C13: =SUM(C4:C12) | D13: =SUM(D4:D12)

Sheet Sprint 3.6 Plan
A1: Sprint 3.6 — Magento Adapter, API Route Tests, Platform Cleanup & Tailwind Finish
A3: Agent | B3: Deliverable | C3: Files (est) | D3: Lines (est) | E3: Status
A4: AR - Arjun | B4: ADR-016 Magento integration + Magento REST adapter (PlatformAdapter) | C4: 3 | D4: 1800 | E4: PLANNED
A5: RG - Rohan | B5: Platform abstraction Phase 3 — final Shopify refs in payments, integrations, collections | C5: 6 | D5: 600 | E5: PLANNED
A6: SP - Sanya | B6: API route integration tests: orders, drivers, routes, webhooks | C6: 4 | D6: 3200 | E6: PLANNED
A7: PK - Priya | B7: Final 2 TODO stubs cleanup + Magento webhook consumer | C7: 3 | D7: 800 | E7: PLANNED
A8: DM - Dev | B8: Tailwind batch 16: admin, widgets, delivery/standard, campaigns/[id], design-system | C8: 5 | D8: 1200 | E8: PLANNED
A9: NK - Nisha | B9: Tailwind batch 17: register, shipping-profiles/[id], shipments, page.tsx, auth/layout | C9: 5 | D9: 1200 | E9: PLANNED
A10: VS - Vikram | B10: Tailwind batch 18: integrations, stores, payments, admin/shops/[id], activity | C10: 5 | D10: 1000 | E10: PLANNED
A11: KS - Kavitha | B11: Platform adapter unit tests: Shopify, WooCommerce, Magento, registry | C11: 4 | D11: 3600 | E11: PLANNED
A12: AM - Aisha | B12: Custom platform adapter (API key auth, field mapping) + generic webhook route | C12: 4 | D12: 1600 | E12: PLANNED
A13: TOTALS | C13: =SUM(C4:C12) | D13: =SUM(D4:D12)

Sheet Sprint 3.7 Plan
A1: Sprint 3.7 Plan — Auth Actions, Core Tests, Shopify TODOs & Deep Tailwind
A3: Agent | B3: Assignee | C3: Task | D3: Deliverables | E3: Est. Lines | F3: Priority
A4: AR (CTO) | B4: Arjun | C4: ADR-017 + Auth Actions Architecture | D4: ADR-017 auth-actions design, dashboard auth-actions.ts real implementation (login/register/forgot-password with API client) | E4: ~800 | F4: P0
A5: RG (Backend Lead) | B5: Rohan | C5: Core module tests: tracking, labels, monitoring | D5: tracking/__tests__/*.test.ts, labels/__tests__/*.test.ts, monitoring/__tests__/*.test.ts | E5: ~2,400 | F5: P0
A6: SP (Full-stack) | B6: Sanya | C6: Core module tests: drivers, orders, routes, zones | D6: drivers/__tests__/*.test.ts, orders/__tests__/*.test.ts, routes/__tests__/*.test.ts, zones/__tests__/*.test.ts | E6: ~3,200 | F6: P0
A7: PK (Sr. Backend) | B7: Priya | C7: Shopify app TODO fixes + shipping-profiles tests | D7: shopify-app webhooks.tsx fixes (user ID mapping, shop config pickup, order DB fetch), shipping-profiles/__tests__/*.test.ts | E7: ~1,800 | F7: P0
A8: AM (Integration) | B8: Aisha | C8: Core module tests: integrations, events, push, shops | D8: integrations/__tests__/*.test.ts, events/__tests__/*.test.ts, push/__tests__/*.test.ts, shops/__tests__/*.test.ts | E8: ~3,000 | F8: P0
A9: KS (QA Lead) | B9: Kavitha | C9: Core module tests: migration + E2E platform adapter flow test | D9: migration/__tests__/*.test.ts, platforms/__tests__/e2e-platform-flow.test.ts (Shopify→WooCommerce→Magento→Custom full flow) | E9: ~2,200 | F9: P1
A10: DM (Frontend) | B10: Deepak | C10: Tailwind Batch 19 (5 pages, 5+ styles) | D10: admin/design-system, widgets, page.tsx (home), drivers, campaigns/[id] | E10: ~600 | F10: P1
A11: NK (Frontend Lead) | B11: Neha | C11: Tailwind Batch 20 (5 pages, 5+ styles) | D11: (auth)/layout, shipments, (auth)/register, admin/shops/[id], admin/page | E11: ~500 | F11: P1
A12: VS (Component Dev) | B12: Vikram | C12: Tailwind Batch 21 (5 pages, 5+ styles) | D12: activity, widget-config, routes/page, routes/[id], orders/local | E12: ~500 | F12: P1
A14: SPRINT 3.7 TOTALS | C14: Auth actions, 14 core module test suites, 4 Shopify TODO fixes, 15 Tailwind pages | E14: ~15,000

Sheet Sprint 3.8 Plan
A1: Sprint 3.8 Plan — Error Boundaries, Security, Route Tests & Tailwind Final
A3: Agent | B3: Assignee | C3: Task | D3: Deliverables | E3: Est. Lines | F3: Priority
A4: AR (CTO) | B4: Arjun | C4: ADR-018 Error Handling + .gitleaks.toml + Security Fix | D4: ADR-018 error-handling-resilience.md, .gitleaks.toml config, fix sk_live/sk_test → sk_example in stores + api-keys pages | E4: ~700 | F4: P0
A5: RG (Backend Lead) | B5: Rohan | C5: API route tests batch 1: auth, billing, campaigns | D5: apps/api/src/routes/__tests__/auth.test.ts, billing.test.ts, campaigns.test.ts | E5: ~3,000 | F5: P0
A6: SP (Full-stack) | B6: Sanya | C6: API route tests batch 2: shipments, collections, integrations | D6: apps/api/src/routes/__tests__/shipments.test.ts, collections.test.ts, integrations.test.ts | E6: ~3,000 | F6: P0
A7: PK (Sr. Backend) | B7: Priya | C7: API route tests batch 3: customers, payments, locations | D7: apps/api/src/routes/__tests__/customers.test.ts, payments.test.ts, locations.test.ts | E7: ~3,000 | F7: P0
A8: AM (Integration) | B8: Aisha | C8: API route tests batch 4: products, users, shops + webhook routes | D8: apps/api/src/routes/__tests__/products.test.ts, users.test.ts, shops.test.ts | E8: ~3,000 | F8: P0
A9: KS (QA Lead) | B9: Kavitha | C9: API route tests batch 5: analytics, admin, support-tickets | D9: apps/api/src/routes/__tests__/analytics.test.ts, admin.test.ts, support-tickets.test.ts | E9: ~3,000 | F9: P0
A10: DM (Frontend) | B10: Deepak | C10: Next.js error boundaries + loading states | D10: error.tsx (root + per-route-group), loading.tsx (root + key pages), not-found.tsx, ErrorBoundary component | E10: ~800 | F10: P0
A11: NK (Frontend Lead) | B11: Neha | C11: Tailwind Batch 22 (7 pages, 4-style tier) | D11: settings, routes, routes/create, locations, delivery, calendar, (auth)/login → all ≤1 inline style | E11: ~500 | F11: P1
A12: VS (Component Dev) | B12: Vikram | C12: Tailwind Batch 23 (7 pages, 3-style tier) + clean dist/ | D12: zones, time-slots, shipping-profiles, orders, notifications, collections, billing → ≤1 inline style; remove tracked dist/ files | E12: ~500 | F12: P1
A14: SPRINT 3.8 TOTALS | C14: ADR-018, security fix, 15 API route test suites, error boundaries, 14 Tailwind pages, dist cleanup | E14: ~17,500

Sheet Sprint 3.9 Plan
A1: Agent | B1: Role | C1: Task | D1: Status | E1: Files | F1: Lines | G1: Test Cases
A2: AR | B2: CTO | C2: CONTRIBUTING.md + Docker Compose + Dockerfile | D2: Done | E2: 4 | F2: 863 | G2: -
A3: RG | B3: Backend Lead | C3: Route tests batch 6: activity-logs, analytics-events, audit, carriers, tracking | D3: Done | E3: 5 | F3: 3974 | G3: 241
A4: SP | B4: Full-stack | C4: Route tests batch 7: orgs, routes-api, permissions, time-slots, zones | D4: Done | E4: 5 | F4: 3591 | G4: 260
A5: PK | B5: Sr. Backend | C5: Route tests batch 8: shipping-profiles, calendar-rules, notification-templates, messages, saved-views | D5: Done | E5: 5 | F5: 4060 | G5: 211
A6: AM | B6: Integration | C6: Route tests batch 9: woocommerce-webhooks, magento-webhooks, custom-webhooks, outbound-webhooks, workflow-orders | D6: Done | E6: 5 | F6: 4229 | G6: 227
A7: KS | B7: QA Lead | C7: Route tests batch 10: workflow-delivery, workflow-drivers, workflow-executions, pos, widget-config | D7: Done | E7: 5 | F7: 4413 | G7: 335
A8: DM | B8: Frontend | C8: DatePicker + Pagination UI components | D8: Done | E8: 3 | F8: 520 | G8: -
A9: NK | B9: Frontend Lead | C9: Tailwind Batch 24: widgets, drivers, campaigns/[id], design-system, register | D9: Done | E9: 5 | F9: ~ | G9: -
A10: VS | B10: Component Dev | C10: Tailwind Batch 25: widget-config, admin, activity, analytics, integrations, admin/users, admin/customers | D10: Done | E10: 7 | F10: ~ | G10: -

Sheet Sprint 4.0 Plan
A1: Agent | B1: Role | C1: Task | D1: Status | E1: Files | F1: Lines | G1: Test Cases
A2: AR | B2: CTO | C2: ADR-019 CI/CD + LICENSE + CI hardening | D2: Done | E2: 3 | F2: 468 | G2: -
A3: RG | B3: Backend Lead | C3: Final 4 route tests: auth-providers, billing-subscriptions, feature-requests, payment-methods | D3: Done | E3: 4 | F3: 3170 | G3: 211
A4: SP | B4: Full-stack | C4: Integration tests: order-lifecycle, auth-flow, billing-flow, webhook-chain | D4: Done | E4: 4 | F4: 4001 | G4: 87
A5: PK | B5: Sr. Backend | C5: Shopify app tests: app-index, app-settings, app-webhooks, app-orders | D5: Done | E5: 4 | F5: 3772 | G5: 237
A6: AM | B6: Integration | C6: Webhook E2E: Shopify, WooCommerce, Magento, cross-platform | D6: Done | E6: 4 | F6: 3676 | G6: 133
A7: KS | B7: QA Lead | C7: Component unit tests: button, card, badge, input, modal, table, date-picker, pagination, error-boundary | D7: Done | E7: 9 | F7: 4822 | G7: 200+
A8: DM | B8: Frontend | C8: 6 new UI components: Breadcrumb, Avatar, Switch, Checkbox, Alert, Progress | D8: Done | E8: 7 | F8: 559 | G8: -
A9: NK | B9: Frontend Lead | C9: Tailwind Batch 26: drivers, widgets, campaigns/[id], design-system, register | D9: Done | E9: 5 | F9: ~ | G9: -
A10: VS | B10: Component Dev | C10: Tailwind Batch 27: routes, locations, delivery, calendar, login, orders/local, routes/[id], routes/create | D10: Done | E10: 8 | F10: ~ | G10: -

Sheet Sprint 4.1 Plan
A1: Agent | B1: Role | C1: Task | D1: Status | E1: Deliverables
A2: AR | B2: CTO | C2: ADR-020 docs architecture + Fumadocs scaffold + AI search config | D2: Planned | E2: ADR-020, apps/docs scaffold
A3: RG | B3: Backend Lead | C3: API reference: OpenAPI spec cleanup + 73 endpoint doc pages | D3: Planned | E3: openapi.json, route docs
A4: SP | B4: Full-stack | C4: Getting Started + Architecture + Self-Hosting guides (MDX) | D4: Planned | E4: 3 MDX guides, env ref
A5: PK | B5: Sr. Backend | C5: SDK scaffold: packages/sdk auto-generated TypeScript client | D5: Planned | E5: packages/sdk package
A6: AM | B6: Integration | C6: Platform adapter guides (Shopify/WooCommerce/Magento/Custom) | D6: Planned | E6: 4 platform MDX files
A7: KS | B7: QA Lead | C7: Testing guide + Contributing guide + ADR browser section | D7: Planned | E7: Testing guide, ADR config
A8: DM | B8: Frontend | C8: Docs theme: dark-first design, landing page, navigation, search | D8: Planned | E8: Custom theme, layout
A9: NK | B9: Frontend Lead | C9: Component gallery: 23 components with live previews + props | D9: Planned | E9: 23 component pages
A10: VS | B10: Component Dev | C10: Workflow engine + notification + billing/RBAC guides | D10: Planned | E10: 5+ MDX guide files

Sheet Sprint 4.2 Plan
A1: Sprint 4.2 — DX Polish, SDK Tests, Seed Data & Driver App Build-Out
A2: Theme: Make the monorepo bootable, SDK production-ready, seed data for demo, driver app screens
A3: Agent | B3: Assignment | C3: Deliverables | D3: Skill(s)
A4: AR - Aarav (CTO) | B4: ADR-021 DX & Monorepo Bootability + turbo.json tuning | C4: ADR-021 (~400 lines), updated turbo.json with proper pipeline (build/dev/lint/test/typecheck/db:generate), workspace package.json fixes, tsconfig references cleanup | D4: system-design
A5: RG - Raj (Backend Lead) | B5: Database seed scripts + .env.example validation | C5: packages/db/src/seed.ts (demo data: 3 orgs, 10 users, 50 orders, 20 drivers, 5 zones, sample shipments), seed command in package.json, .env.example audit with all required vars documented | D5: system-design
A6: PK - Priya (Sr. Backend) | B6: SDK test suite + publish config | C6: packages/sdk/__tests__/client.test.ts, orders.test.ts, drivers.test.ts, zones.test.ts, shipments.test.ts, errors.test.ts (~6 test files, 200+ cases), tsup.config.ts for build, package.json publish fields (main/module/types/exports) | D6: testing-strategy
A7: SP - Sanjay (Full-stack) | B7: Driver app screens build-out | C7: Enhanced HomeScreen (stats dashboard), ShipmentListScreen (filterable list with status badges), RouteDetailScreen (turn-by-turn with map placeholder), DeliveryProofScreen (camera + signature capture), shared hooks (useAuth, useApi, useLocation) | D7: frontend-design
A8: DM - Dev (Frontend) | B8: Tracking page polish + live map | C8: TrackingLandingPage redesign (order lookup), ShipmentTracker (status timeline + live map placeholder with Leaflet stub), DriverCard (ETA + driver info), responsive mobile-first layout, Tailwind + dark theme | D8: frontend-design
A9: NK - Neha (Frontend Lead) | B9: Dashboard remaining gaps + settings page | C9: Settings page (/settings with tabs: profile, organization, billing, integrations, API keys), Notification preferences page, Activity feed realtime indicator, remaining page polish (any pages missing loading/error states) | D9: frontend-design
A10: VS - Vikram (Component Dev) | B10: New shared components + Storybook-style gallery page | C10: FileUpload component, Combobox (searchable select), Timeline component, StatusBadge (delivery-specific), CommandPalette (CMD+K), update component index.ts exports, update docs gallery MDX for new components | D10: frontend-design
A11: KS - Kavitha (QA Lead) | B11: SDK tests + docs app tests + smoke test script | C11: apps/docs/__tests__/build.test.ts (docs build smoke), packages/sdk/__tests__/integration.test.ts (mock server E2E), scripts/smoke-test.sh (boots API, hits /health, verifies response), CI workflow update for smoke test step | D11: testing-strategy
A12: AM - Aisha (Integration) | B12: Webhook delivery dashboard + integration health page | C12: Dashboard /integrations/webhooks page (delivery log table, retry button, status indicators), /integrations/health page (integration status cards with last-check timestamps), API routes for webhook delivery history query | D12: frontend-design

Sheet Sprint 4.3 Plan
A1: Sprint 4.3 — witylogix CLI Deployment Tool + AI Engineer Onboarding
A2: Theme: One-line VM deployment, CLI subcommands, Caddy SSL, AI diagnostics, production Docker Compose
A3: Agent | B3: Assignment | C3: Deliverables | D3: Skill(s)
A4: AR - Aarav (CTO) | B4: ADR-022 CLI Architecture + main entrypoint | C4: docs/adr/ADR-022-cli-deployment-tool.md (~500 lines), infra/cli/witylogix (main script ~300 lines with subcommand routing, help, version, color output, config loader) | D4: system-design
A5: RG - Raj (Backend) | B5: deploy + install subcommands | C5: infra/cli/commands/install.sh (~200 lines — Docker bootstrap, dir creation, image pull), infra/cli/commands/deploy.sh (~300 lines — build/pull, migrate, seed, start, health wait, zero-downtime detection) | D5: system-design
A6: PK - Priya (Sr. Backend) | B6: backup + restore + upgrade subcommands | C6: infra/cli/commands/backup.sh (~200 lines — pg_dump with compression, S3 upload optional, rotation), infra/cli/commands/restore.sh (~150 lines), infra/cli/commands/upgrade.sh (~200 lines — pull, migrate, rolling restart) | D6: system-design
A7: SP - Sanjay (Full-stack) | B7: ssl + env subcommands | C7: infra/cli/commands/ssl.sh (~200 lines — Caddy config generator, domain setup, cert check), infra/cli/commands/env.sh (~250 lines — interactive .env configurator, validation, secret generation) | D7: system-design
A8: ZR - Zara (AI Engineer) | B8: ai setup + ai diagnose subcommands | C8: infra/cli/commands/ai.sh (~300 lines — Claude API key config, log collector, diagnostic prompt builder, structured output parser), infra/cli/templates/ai-diagnose-prompt.txt | D8: system-design
A9: NK - Neha (Frontend Lead) | B9: dev subcommand | C9: infra/cli/commands/dev.sh (~250 lines — dependency checker, port allocator, env validator, turbo boot with status table, process manager, graceful shutdown handler) | D9: system-design
A10: DM - Dev (Frontend) | B10: status + doctor subcommands | C10: infra/cli/commands/status.sh (~200 lines — HTTP probes for all services, formatted table), infra/cli/commands/doctor.sh (~250 lines — disk/mem/ports/DNS/Docker/connectivity checks, report generator) | D10: system-design
A11: KS - Kavitha (QA Lead) | B11: CLI tests + init subcommand | C11: infra/cli/commands/init.sh (~200 lines — contributor setup, deps install, prisma generate, seed, smoke test), infra/cli/__tests__/test-cli.sh (~300 lines — test harness for all subcommands), CI workflow update | D11: testing-strategy
A12: VS - Vikram (Component) | B12: logs + scale + destroy subcommands | C12: infra/cli/commands/logs.sh (~150 lines — multi-service log tailing with color), infra/cli/commands/scale.sh (~100 lines — Docker Compose scale wrapper), infra/cli/commands/destroy.sh (~120 lines — clean teardown with confirmation) | D12: system-design
A13: AM - Aisha (Integration) | B13: Caddy templates + production Docker Compose | C13: infra/cli/templates/Caddyfile (~80 lines — reverse proxy for api/app/docs with auto-SSL), infra/docker-compose.prod.yml (~200 lines — production-grade with healthchecks, restart policies, resource limits, Caddy service), infra/cli/templates/env.template | D13: system-design

Sheet Sprint 4.4 Plan
A1: Sprint 4.4 — E2E Testing, Event Bus, Platform Admin & Gap Closure
A2: Planned: 2026-03-10 | Focus: E2E framework, event bus, platform admin, package maturity
A4: Agent | B4: Role | C4: Deliverable | D4: Files (est) | E4: Lines (est) | F4: Status
A5: AR (Arjun) | B5: CTO / Architect | C5: ADR-023 E2E Testing & Event Bus architecture; Prisma schema additions (authProvider, authSession, platformAdmin, posConfig models) | D5: 3 | E5: ~900 | F5: PLANNED
A6: RG (Rohan) | B6: Backend Lead | C6: Event Bus with Redis Streams — typed event emitter, pub/sub, event store, replay, dead letter queue | D6: 8 | E6: ~2,400 | F6: PLANNED
A7: PK (Priya) | B7: Sr. Backend | C7: Auth provider registry core module — provider CRUD, session management, token validation, multi-tenant | D7: 6 | E7: ~1,800 | F7: PLANNED
A8: SP (Sanya) | B8: Full-stack | C8: Workflow integration triggers — auto-trigger workflows from order/shipment/driver API endpoints + Socket.io events | D8: 5 | E8: ~1,500 | F8: PLANNED
A9: ZR (Zara) | B9: AI Engineer | C9: AI-powered monitoring — anomaly detection for delivery SLAs, predictive ETA model, alert recommendations engine | D9: 6 | E9: ~2,000 | F9: PLANNED
A10: NK (Neha) | B10: Frontend Lead | C10: Activity log redesign — real-time filterable event stream page with timeline view, user actions, system events | D10: 3 | E10: ~900 | F10: PLANNED
A11: DM (Dhruv) | B11: Frontend | C11: Design tokens page — interactive token reference (colors, spacing, typography, shadows) + shadcn/ui component preview gallery | D11: 3 | E11: ~1,100 | F11: PLANNED
A12: VS (Vikram) | B12: Component Dev | C12: Package maturity — add build scripts (tsup) + test scripts to framework, types, validators, workflows packages; fix exports | D12: 12 | E12: ~1,600 | F12: PLANNED
A13: KS (Kavitha) | B13: QA Lead | C13: E2E test framework — Playwright setup, page objects, 5 critical flow tests (auth, order CRUD, driver assign, tracking, webhooks) | D13: 10 | E13: ~3,000 | F13: PLANNED
A14: AM (Aisha) | B14: Integration | C14: Webhook management page redesign + event log viewer page + Shopify workflow bridge (order webhook → workflow trigger) | D14: 5 | E14: ~1,800 | F14: PLANNED
A16: TOTALS | D16: ~61 files | E16: ~17,000 lines

Sheet Sprint 4.5 Plan (Done)
A1: Agent | B1: Role | C1: Sprint 4.5 Task | D1: Files/Packages | E1: Key Deliverables | F1: Competitive Benchmark | G1: Status
A2: AR | B2: CTO / Architect | C2: Route Timeline Dispatcher Dashboard (Routific-quality) | D2: apps/dashboard/src/app/(dashboard)/dispatch/, packages/core/src/dispatch/ | E2: Map with color-coded driver routes + timeline view (8am-7pm). Unscheduled/Scheduled toggle. Drag-and-drop route editing. Real-time stats bar (drivers, stops, km, time). | F2: Routific: 10 color-coded routes, 540 stops, timeline per driver | G2: PLANNED
A3: NK | B3: Frontend Lead | C3: Checkout Date/Time Picker Widget (Pickeasy-quality) | D3: packages/checkout-widget/, extensions/checkout-ui/ | E3: Embeddable widget: date calendar, time slot grid with capacity indicators, zone-based rate display, blackout dates, cut-off times, zipcode validation, prep time settings. | F3: Pickeasy: 8K merchants, slot limits, blackout, zip validation, $9.99-49.99 | G3: PLANNED
A4: DM | B4: Frontend Dev | C4: Customer Self-Service Portal | D4: apps/customer-portal/ | E4: Next.js portal: order history with timeline, live tracking, rescheduling flow, delivery preferences (safe place, instructions), driver ratings, notification preferences. | F4: Route4Me: only platform with self-service portal. First-mover for open-source | G4: PLANNED
A5: RG | B5: Backend Lead | C5: Slot Engine API & Capacity Management | D5: packages/core/src/slots/, apps/api/src/routes/checkout/ | E5: Slot availability API, capacity limits per slot/day, zone-rate calculator, order deadline engine (e.g. Friday pickup by Thu 4pm), cart integration endpoints. | F5: Pickeasy: order deadlines, daily limits, product-specific slots | G5: PLANNED
A6: PK | B6: Sr. Backend | C6: POD v2: Photo + Signature + QR + Status Timeline | D6: packages/core/src/pod/, apps/api/src/routes/pod/ | E6: Multi-method POD: photo capture, e-signature pad, QR/barcode scan. Delivery status timeline (Planned → Out for Delivery → Delivered + photo). S3/R2 storage. | F6: Routific: status timeline with photo. Fleetbase: QR+signature+manual | G6: PLANNED
A7: SP | B7: Full-stack | C7: Customer Notification Engine v2 + SMS/WhatsApp | D7: packages/core/src/notifications-v2/, apps/api/src/routes/notifications/ | E7: Multi-channel: email + SMS (Twilio) + WhatsApp (Meta Business) + push. Template engine. SMS with tracking link + time window (Routific pattern). Delivery webhooks. | F7: Routific: SMS with tracking link + time window. ScrollEngine: WhatsApp | G7: PLANNED
A8: VS | B8: Component Dev | C8: Checkout & Dispatch Component Library | D8: packages/checkout-widget/src/, apps/dashboard/src/components/dispatch/ | E8: Checkout: DatePicker, TimeSlotGrid, ZoneMap, DeliveryOptions, AddressAutocomplete. Dispatch: RouteTimeline, DriverCard, StopMarker, StatsBanner. | F8: Routific timeline + Pickeasy checkout as UX reference | G8: PLANNED
A9: KS | B9: QA Lead | C9: E2E: Dispatch, Checkout & Customer Portal | D9: tests/e2e/specs/dispatch/, tests/e2e/specs/checkout/, tests/e2e/specs/portal/ | E9: Playwright suites: dispatch timeline interaction, checkout widget slot selection, customer portal auth + reschedule, POD photo upload, SMS notification delivery. | F9: Full coverage for all Sprint 4.5 customer-facing features | G9: PLANNED
A10: AM | B10: Integration | C10: Shopify Checkout Extension + Google Maps/Calendar | D10: extensions/checkout-ui/, packages/core/src/integrations/google/ | E10: Shopify checkout extension with embedded date/time widget. Google Maps for zone visualization. Google Calendar sync for merchant order reminders. | F10: Pickeasy: Google Maps + Calendar. Zapiet: Shopify certified | G10: PLANNED
A11: ZR | B11: AI Engineer | C11: Smart Slot Recommendation + ML ETA Engine | D11: packages/core/src/ai-slots/, packages/core/src/ai-eta/ | E11: ML slot recommender: demand prediction, driver availability forecast. Traffic-aware ETA model (start with 3-5 models, target Routific's 179 as long-term goal). | F11: Routific: 179 ML models. Nobody has AI slot recommendation — first-mover | G11: PLANNED
A13: THEME | B13: Sprint 4.5: Customer Experience & Checkout Enhancement — Routific-quality dispatcher dashboard, Pickeasy-quality checkout widget, customer self-service portal, POD v2 with status timeline, SMS/WhatsApp notifications, AI slot recommendation engine.
A14: BENCHMARKS | B14: UX: Routific dispatcher timeline + driver app + POD flow + SMS tracking. Checkout: Pickeasy date/time picker + slot capacity + blackout + zip validation. Portal: Route4Me self-service. Notifications: Routific SMS + ScrollEngine WhatsApp.

Sheet Sprint 4.7 Plan (Done)
A1: Sprint 4.7 — Telematics, Traffic-Aware ETA & Integration Ecosystem
A2: Agent | B2: Role | C2: Task | D2: Files/Packages | E2: Key Deliverables | F2: Gap Ref | G2: Status
A3: AR - Arjun | B3: CTO | C3: Telematics Architecture ADR-026 + Fleet Dashboard | D3: docs/adr/, apps/dashboard/src/app/(dashboard)/fleet/ | E3: ADR-026 telematics gateway; Fleet dashboard page with vehicle status, fuel, diagnostics; Fleet overview API endpoints | F3: G-11 | G3: ⬜
A4: DM - Deepak | B4: Frontend | C4: Courier Partner Directory UI + Partner Onboarding | D4: apps/dashboard/src/app/(dashboard)/partners/ | E4: Partner directory page with search/filter, partner detail cards, onboarding wizard (3-step), courier comparison view, partner settings | F4: G-14 | G4: ⬜
A5: NK - Nikhil | B5: Frontend Lead | C5: Fleet Map & Telematics Dashboard Components | D5: apps/dashboard/src/components/fleet/ | E5: Vehicle tracker map (real-time positions), fuel gauge widget, diagnostic alerts panel, driver behavior heatmap, idle time chart, fleet stats cards | F5: G-11 | G5: ⬜
A6: RG - Rahul | B6: Backend Lead | C6: Telematics Adapter Layer (Samsara + Geotab) | D6: packages/core/src/integrations/telematics/ | E6: TelematicsAdapter interface, Samsara client (REST API v1), Geotab client (MyGeotab), vehicle position/fuel/diagnostics polling, event webhooks, rate limiting | F6: G-11 | G6: ⬜
A7: SP - Sanjay | B7: Full-stack | C7: Invoice Completion + QuickBooks/Xero Integration | D7: packages/core/src/invoicing/, packages/core/src/integrations/accounting/ | E7: Configurable billing rules (per-delivery/mile/hour/subscription), email invoice delivery, QuickBooks OAuth2 adapter, Xero OAuth2 adapter, accounting sync API | F7: G-13 | G7: ⬜
A8: VS - Vikram | B8: Component Dev | C8: Fleet & Partner UI Components + Courier Cards | D8: apps/dashboard/src/components/fleet/, apps/dashboard/src/components/partners/ | E8: Vehicle status card, fuel gauge (SVG), diagnostic badge, speed chart, courier partner card, rate comparison table, partner badge, SLA indicator | F8: G-11, G-14 | G8: ⬜
A9: PK - Priya | B9: Sr. Backend | C9: Courier Partner Adapters (Onfleet, Stuart, Uber Direct) | D9: packages/core/src/integrations/couriers/ | E9: CourierAdapter interface, Onfleet client (Tasks API), Stuart client (Jobs API), Uber Direct client (Deliveries API), rate quotes, dispatch, tracking, webhook handlers | F9: G-14 | G9: ⬜
A10: KS - Kavitha | B10: QA Lead | C10: Telematics + Courier + Invoice Integration Tests | D10: tests/integration/telematics/, tests/integration/couriers/, tests/integration/invoicing/ | E10: Samsara adapter tests, Geotab adapter tests, Onfleet/Stuart/Uber Direct tests, invoice billing rules tests, QuickBooks/Xero sync tests, 200+ test cases | F10: G-11, G-13, G-14 | G10: ⬜
A11: AM - Aisha | B11: Integration | C11: Traffic-Aware ETA v2 + Google Directions Integration | D11: packages/core/src/ai-eta-v2/, packages/core/src/integrations/traffic/ | E11: Google Directions API client (distance matrix, traffic data), TomTom Traffic API adapter, traffic-aware routing, ETA adjustment pipeline, real-time traffic overlay API | F11: G-12 | G11: ⬜
A12: ZR - Zara | B12: AI Engineer | C12: ML ETA Engine v2 — Traffic-Aware Multi-Model | D12: packages/core/src/ai-eta-v2/ | E12: Traffic zone classifier, time-of-day model, day-of-week model, distance-decay model, historical delivery model, weather impact model, ensemble with confidence intervals, auto-calibration, model performance tracker | F12: G-12 | G12: ⬜

Sheet Sprint 4.8 Plan
A1: Agent | B1: Role | C1: Task | D1: Deliverables | E1: Est. Lines | F1: Status
A2: AR - Arjun | B2: CTO | C2: ADR-027 AI Demand Prediction Architecture + Platform Health Dashboard | D2: ADR-027 doc, demand-prediction types, platform health page, system status API | E2: 3000 | F2: Planned
A3: DM - Deepak | B3: Frontend | C3: Invoice Management Dashboard + Payment Tracking UI | D3: Invoice list page, invoice detail, payment history, invoice PDF preview component | E3: 2500 | F3: Planned
A4: NK - Nikhil | B4: Frontend Lead | C4: Courier Live Tracking Map + Dispatch Console | D4: Live courier map, dispatch console, courier assignment panel, delivery timeline | E4: 2400 | F4: Planned
A5: RG - Rahul | B5: Backend Lead | C5: Courier Webhook Handlers + Partner Rating Engine | D5: Webhook processors for Onfleet/Stuart/Uber, partner rating service, SLA tracker | E5: 3500 | F5: Planned
A6: SP - Sanjay | B6: Full-stack | C6: Invoice PDF Generation + Payment Gateway Integration | D6: PDF invoice generator (html-pdf), Stripe payment links, payment reconciliation | E6: 4000 | F6: Planned
A7: VS - Vikram | B7: Component Dev | C7: Invoice & Payment UI Components + Courier Tracking Cards | D7: Invoice table, payment status badge, amount display, courier tracking card, delivery ETA card | E7: 2800 | F7: Planned
A8: PK - Priya | B8: Sr. Backend | C8: Courier Partner Rating + Multi-Courier Routing Engine | D8: Partner performance scoring, auto-courier selection v2, cost optimization, SLA enforcement | E8: 3800 | F8: Planned
A9: KS - Kavitha | B9: QA Lead | C9: Invoice + Payment + Courier Dispatch Integration Tests | D9: Invoice generation tests, payment flow tests, courier dispatch tests, webhook handler tests | E9: 2000 | F9: Planned
A10: AM - Aisha | B10: Integration | C10: AI Demand Prediction Data Pipeline + Feature Store | D10: Historical delivery aggregator, time-series feature extractor, demand forecasting pipeline | E10: 4500 | F10: Planned
A11: ZR - Zara | B11: AI Engineer | C11: AI Demand Prediction Models + Smart Scheduling Engine | D11: Demand forecasting models (ARIMA-like, seasonal decomposition, zone clustering), smart slot optimizer | E11: 5500 | F11: Planned
